Workbook

Sheet Overzicht
A1: Belgische bedrijven – kandidaten voor gratis test (onderzoek tijdsbesparing door AI)
A3: Verzameld op 27-28 september 2026 via webzoekresultaten (fragmenten van bedrijfswebsites en openbare bedrijvengidsen).
A4: Bedrijfswebsites, Voka/Unizo-ledenlijsten en Trends Top konden niet rechtstreeks geopend worden (netwerkbeleid van de omgeving). Alle gegevens zijn dus niet op de website zelf nagekeken — controleer vóór contact.
A5: Groottecriteria (medewerkers, aantal panden) staan zelden publiek: de kolom 'Opmerking' zegt wat bekend is; 'omvang niet geverifieerd' betekent dat het criterium niet bevestigd is.
A6: Lege cel bij e-mail/telefoon = niet gevonden in de zoekresultaten. Persoonlijke adressen zijn gemarkeerd in de opmerking.
A7: Doel was 100 per sector; de zoeklimiet van de sessie (200 zoekopdrachten) liet dit aantal niet toe.
A9: Sector | B9: Subcategorie | C9: Aantal | D9: Met e-mail
A10: Boekhouding | B10: Zelfstandige boekhouder | C10: =COUNTIF('Boekhouding'!$C:$C,B10) | D10: =COUNTIFS('Boekhouding'!$C:$C,B10,'Boekhouding'!$F:$F,"?*")
A11: Boekhouding | B11: Klein kantoor (2-10 medewerkers) | C11: =COUNTIF('Boekhouding'!$C:$C,B11) | D11: =COUNTIFS('Boekhouding'!$C:$C,B11,'Boekhouding'!$F:$F,"?*")
A12: Boekhouding | B12: Groter accountantskantoor (meerdere vestigingen) | C12: =COUNTIF('Boekhouding'!$C:$C,B12) | D12: =COUNTIFS('Boekhouding'!$C:$C,B12,'Boekhouding'!$F:$F,"?*")
A13: Boekhouding | B13: Sociaal secretariaat | C13: =COUNTIF('Boekhouding'!$C:$C,B13) | D13: =COUNTIFS('Boekhouding'!$C:$C,B13,'Boekhouding'!$F:$F,"?*")
A14: Boekhouding | B14: Totaal sector (doel: 100) | C14: =SUM(C10:C13) | D14: =SUM(D10:D13)
A15: Advocaten & consultancy | B15: Klein advocatenkantoor (≤5) | C15: =COUNTIF('Advocaten & consultancy'!$C:$C,B15) | D15: =COUNTIFS('Advocaten & consultancy'!$C:$C,B15,'Advocaten & consultancy'!$F:$F,"?*")
A16: Advocaten & consultancy | B16: Notariskantoor | C16: =COUNTIF('Advocaten & consultancy'!$C:$C,B16) | D16: =COUNTIFS('Advocaten & consultancy'!$C:$C,B16,'Advocaten & consultancy'!$F:$F,"?*")
A17: Advocaten & consultancy | B17: Bedrijfsadvies / HR-consultancy | C17: =COUNTIF('Advocaten & consultancy'!$C:$C,B17) | D17: =COUNTIFS('Advocaten & consultancy'!$C:$C,B17,'Advocaten & consultancy'!$F:$F,"?*")
A18: Advocaten & consultancy | B18: Totaal sector (doel: 100) | C18: =SUM(C15:C17) | D18: =SUM(D15:D17)
A19: Transport & logistiek | B19: Transportbedrijf (eigen wagenpark) | C19: =COUNTIF('Transport & logistiek'!$C:$C,B19) | D19: =COUNTIFS('Transport & logistiek'!$C:$C,B19,'Transport & logistiek'!$F:$F,"?*")
A20: Transport & logistiek | B20: Koeriersbedrijf | C20: =COUNTIF('Transport & logistiek'!$C:$C,B20) | D20: =COUNTIFS('Transport & logistiek'!$C:$C,B20,'Transport & logistiek'!$F:$F,"?*")
A21: Transport & logistiek | B21: Verhuisfirma | C21: =COUNTIF('Transport & logistiek'!$C:$C,B21) | D21: =COUNTIFS('Transport & logistiek'!$C:$C,B21,'Transport & logistiek'!$F:$F,"?*")
A22: Transport & logistiek | B22: Totaal sector (doel: 100) | C22: =SUM(C19:C21) | D22: =SUM(D19:D21)
A23: Bouw | B23: Algemene aannemer | C23: =COUNTIF('Bouw'!$C:$C,B23) | D23: =COUNTIFS('Bouw'!$C:$C,B23,'Bouw'!$F:$F,"?*")
A24: Bouw | B24: Installatiebedrijf (elektriciteit) | C24: =COUNTIF('Bouw'!$C:$C,B24) | D24: =COUNTIFS('Bouw'!$C:$C,B24,'Bouw'!$F:$F,"?*")
A25: Bouw | B25: Installatiebedrijf (sanitair/verwarming) | C25: =COUNTIF('Bouw'!$C:$C,B25) | D25: =COUNTIFS('Bouw'!$C:$C,B25,'Bouw'!$F:$F,"?*")
A26: Bouw | B26: Renovatiebedrijf | C26: =COUNTIF('Bouw'!$C:$C,B26) | D26: =COUNTIFS('Bouw'!$C:$C,B26,'Bouw'!$F:$F,"?*")
A27: Bouw | B27: Totaal sector (doel: 100) | C27: =SUM(C23:C26) | D27: =SUM(D23:D26)
A28: Vastgoed | B28: Makelaarskantoor | C28: =COUNTIF('Vastgoed'!$C:$C,B28) | D28: =COUNTIFS('Vastgoed'!$C:$C,B28,'Vastgoed'!$F:$F,"?*")
A29: Vastgoed | B29: Verhuur- & beheerkantoor | C29: =COUNTIF('Vastgoed'!$C:$C,B29) | D29: =COUNTIFS('Vastgoed'!$C:$C,B29,'Vastgoed'!$F:$F,"?*")
A30: Vastgoed | B30: Syndicus / beheerkantoor | C30: =COUNTIF('Vastgoed'!$C:$C,B30) | D30: =COUNTIFS('Vastgoed'!$C:$C,B30,'Vastgoed'!$F:$F,"?*")
A31: Vastgoed | B31: Kleinere vastgoedontwikkelaar | C31: =COUNTIF('Vastgoed'!$C:$C,B31) | D31: =COUNTIFS('Vastgoed'!$C:$C,B31,'Vastgoed'!$F:$F,"?*")
A32: Vastgoed | B32: Totaal sector (doel: 100) | C32: =SUM(C28:C31) | D32: =SUM(D28:D31)

Sheet Boekhouding
A1: Bedrijfsnaam | B1: Sector | C1: Subcategorie | D1: Website | E1: Plaats | F1: E-mailadres | G1: Telefoon | H1: Opmerking (omvang / verificatie)
A2: Castagna Accountancy | B2: Boekhouding | C2: Zelfstandige boekhouder | D2: castagna.be | E2: Maasmechelen | F2: hello@castagna.be | G2: 0487 95 86 99 | H2: gsm-nummer; waarschijnlijk eenmanszaak
A3: Fidius (Van Bouwel Severinus) | B3: Boekhouding | C3: Zelfstandige boekhouder | D3: fidius.be | E3: Essen | F3: info@fidius.be | H3: fiscalist; geen telefoon in zoekresultaat
A4: GVP Consult | B4: Boekhouding | C4: Zelfstandige boekhouder | E4: Hasselt | G4: 0491 86 96 28 | H4: CommV, kleinschalig; geen publiek e-mailadres gevonden
A5: ND-Consult | B5: Boekhouding | C5: Zelfstandige boekhouder | D5: nd-consult.be | E5: Oostende | H5: fiscaal accountant; contact via formulier op website
A6: Sandra Vandebosch | B6: Boekhouding | C6: Zelfstandige boekhouder | D6: svandebosch.be | E6: Tongeren | G6: 0486 11 52 07 | H6: zelfstandig boekhouder-fiscalist; op afspraak; geen publiek e-mailadres gevonden
A7: A & I Accountants | B7: Boekhouding | C7: Klein kantoor (2-10 medewerkers) | D7: edcweb.be | E7: Aalst | F7: info@edcweb.be | G7: 053 68 43 80 | H7: omvang niet geverifieerd
A8: Academ Accountants | B8: Boekhouding | C8: Klein kantoor (2-10 medewerkers) | D8: academ.be | E8: Izegem | F8: info@academ.be | G8: +32 51 31 70 27 | H8: omvang niet geverifieerd
A9: Accountancy Van Poucke | B9: Boekhouding | C9: Klein kantoor (2-10 medewerkers) | D9: pia.be | E9: Sint-Niklaas | F9: info@accountancyvanpoucke.be | G9: 03 722 91 00 | H9: omvang niet geverifieerd
A10: Accountantskantoor Reynders & Co | B10: Boekhouding | C10: Klein kantoor (2-10 medewerkers) | E10: Sint-Truiden | G10: +32 11 70 20 70 | H10: geen e-mail gevonden
A11: Actabo | B11: Boekhouding | C11: Klein kantoor (2-10 medewerkers) | D11: actabo.be | E11: Sint-Truiden | F11: info@actabo.be | G11: 011 76 33 01 | H11: omvang niet geverifieerd
A12: Adfibo Accountants | B12: Boekhouding | C12: Klein kantoor (2-10 medewerkers) | D12: adfibo.be | E12: Antwerpen | F12: info@adfibo.be | G12: +32 3 644 68 40 | H12: ±7 medewerkers
A13: Adfisc Accountancy | B13: Boekhouding | C13: Klein kantoor (2-10 medewerkers) | D13: adfisc.be | E13: Roeselare | F13: info@adfisc.be | G13: 051 31 77 22 | H13: omvang niet geverifieerd
A14: ATACS | B14: Boekhouding | C14: Klein kantoor (2-10 medewerkers) | D14: atacs.be | E14: Oostende | F14: info@atacs.be | G14: 059 50 94 73 | H14: klein kantoor volgens website
A15: AZ Accounting | B15: Boekhouding | C15: Klein kantoor (2-10 medewerkers) | D15: azaccounting.be | E15: Antwerpen | F15: info@azaccounting.be | G15: +32 3 271 07 77 | H15: omvang niet geverifieerd
A16: B&R Accountants | B16: Boekhouding | C16: Klein kantoor (2-10 medewerkers) | D16: bnr.be | E16: Brasschaat | F16: mail@bnr.be | H16: omvang niet geverifieerd
A17: Birver Accountants | B17: Boekhouding | C17: Klein kantoor (2-10 medewerkers) | D17: birver.be | E17: Brasschaat | F17: info@birver.be | G17: 03 295 87 74 | H17: omvang niet geverifieerd
A18: Bocon | B18: Boekhouding | C18: Klein kantoor (2-10 medewerkers) | D18: bocon.be | E18: Antwerpen | G18: 03 227 55 22 | H18: klein kantoor; geen e-mail gevonden
A19: Boekhoudkantoor Bart Van Nooten | B19: Boekhouding | C19: Klein kantoor (2-10 medewerkers) | D19: boekhoudkantoorvannooten.be | E19: Mol / Turnhout | G19: 014 55 85 99 | H19: 2 kantoren; geen e-mail gevonden
A20: Brasschaats Boekhoudkantoor (BRBO) | B20: Boekhouding | C20: Klein kantoor (2-10 medewerkers) | D20: brasschaatsboekhoudkantoor.be | E20: Brasschaat | F20: info@brbo.be | H20: omvang niet geverifieerd
A21: Comptamatique | B21: Boekhouding | C21: Klein kantoor (2-10 medewerkers) | D21: comptamatique.be | E21: Brussel | G21: 02 511 12 50 | H21: >100 actieve klanten; geen e-mail gevonden
A22: ComptaTeam | B22: Boekhouding | C22: Klein kantoor (2-10 medewerkers) | D22: comptateam.be | E22: Namur | F22: info@comptateam.be | G22: +32 81 72 18 99 | H22: omvang niet geverifieerd
A23: De Neef & Partners (PIA) | B23: Boekhouding | C23: Klein kantoor (2-10 medewerkers) | D23: deneef.be | E23: Sint-Niklaas | F23: info@deneef.be | G23: +32 3 780 98 80 | H23: omvang niet geverifieerd
A24: Dedhac | B24: Boekhouding | C24: Klein kantoor (2-10 medewerkers) | D24: dedhac.be | E24: Heule (Kortrijk) | F24: info@dedhac.be | G24: 056 36 08 33 | H24: vennootschappen en eenmanszaken; omvang niet geverifieerd
A25: Dfisc | B25: Boekhouding | C25: Klein kantoor (2-10 medewerkers) | D25: dfisc.be | E25: Brugge | F25: office@dfisc.be | G25: 050 39 25 23 | H25: omvang niet geverifieerd
A26: Divo | B26: Boekhouding | C26: Klein kantoor (2-10 medewerkers) | D26: accountantdivo.be | E26: Aalter | G26: +32 9 336 82 28 | H26: 2 partners + 2 zelfstandige medewerkers; geen publiek e-mailadres gevonden
A27: EBS Finance West | B27: Boekhouding | C27: Klein kantoor (2-10 medewerkers) | D27: ebsfinancewest.be | E27: Kortrijk | F27: administratie@ebsfinancewest.be | G27: 056 35 45 56 | H27: omvang niet geverifieerd
A28: Eyckmans & Co Accountantskantoor | B28: Boekhouding | C28: Klein kantoor (2-10 medewerkers) | E28: Brugge | G28: 050 32 03 49 | H28: geen e-mail gevonden
A29: FGDS – Fiduciaire Générale de Services | B29: Boekhouding | C29: Klein kantoor (2-10 medewerkers) | D29: fgds.be | E29: Liège | F29: fgds@skynet.be | H29: omvang niet geverifieerd
A30: Fiduciaire Associés | B30: Boekhouding | C30: Klein kantoor (2-10 medewerkers) | D30: fiduciaireassocies.be | E30: Erpent (Namur) | F30: info@fiduciaireassocies.be | G30: +32 81 60 08 99 | H30: omvang niet geverifieerd
A31: Fiduciaire Dirigeance | B31: Boekhouding | C31: Klein kantoor (2-10 medewerkers) | D31: dirigeance.be | E31: Charleroi | F31: info@dirigeance.be | G31: +32 71 60 98 10 | H31: omvang niet geverifieerd
A32: Fiduciaire Hainaut Tax Consulting | B32: Boekhouding | C32: Klein kantoor (2-10 medewerkers) | D32: ht-consult.be | E32: Tournai | F32: info@ht-consult.be | G32: +32 490 40 52 22 | H32: omvang niet geverifieerd
A33: Fiduciaire Leclef | B33: Boekhouding | C33: Klein kantoor (2-10 medewerkers) | D33: fiduciaire-leclef.be | E33: Charleroi | F33: fiduciaire.leclef@gmail.com | G33: 071 42 34 47 | H33: omvang niet geverifieerd
A34: Fiduciaire Liégeoise | B34: Boekhouding | C34: Klein kantoor (2-10 medewerkers) | E34: Liège | F34: christian.heusicom@fiduciaire-liegeoise.be | G34: +32 4 229 38 68 | H34: persoonlijk adres
A35: Fiduciaire Pardoen | B35: Boekhouding | C35: Klein kantoor (2-10 medewerkers) | D35: pardoen.be | E35: Jumet (Charleroi) | G35: 071 25 93 25 | H35: geen algemeen e-mailadres
A36: Fiduciaire Sobelfisc | B36: Boekhouding | C36: Klein kantoor (2-10 medewerkers) | D36: sobelfisc.com | E36: Namur | F36: fiduciaire@sobelfisc.com | G36: 081 47 07 44 | H36: omvang niet geverifieerd
A37: Fidutop | B37: Boekhouding | C37: Klein kantoor (2-10 medewerkers) | D37: fidutop.be | E37: Liège | F37: info@fidutop.be | G37: 04 247 32 22 | H37: omvang niet geverifieerd
A38: Fiscopti | B38: Boekhouding | C38: Klein kantoor (2-10 medewerkers) | D38: fiscopti.be | E38: Antwerpen | G38: +32 3 257 31 66 | H38: e-mail afgeschermd in zoekresultaat
A39: Fiscorum | B39: Boekhouding | C39: Klein kantoor (2-10 medewerkers) | D39: fiscorum.be | E39: Zwijnaarde (Gent) | F39: info@fiscorum.be | G39: 09 221 57 45 | H39: accountants & belastingconsulenten; omvang niet geverifieerd
A40: Haerts - Dekeyser Accountancy | B40: Boekhouding | C40: Klein kantoor (2-10 medewerkers) | D40: boekhouder.gent | E40: Wondelgem (Gent) | F40: info@hda.gent | G40: +32 9 233 44 98 | H40: omvang niet geverifieerd
A41: HB Accountants | B41: Boekhouding | C41: Klein kantoor (2-10 medewerkers) | D41: hbaccountants.be | E41: Turnhout | F41: info@hbaccountants.be | G41: +32 14 70 35 50 | H41: omvang niet geverifieerd
A42: Heidi Hemelsoet & Team | B42: Boekhouding | C42: Klein kantoor (2-10 medewerkers) | D42: heidihemelsoet.be | E42: Gent | F42: info@heidihemelsoet.be | H42: omvang niet geverifieerd
A43: Impacct Accountants | B43: Boekhouding | C43: Klein kantoor (2-10 medewerkers) | D43: impacct.be | E43: Leuven | F43: info@impacct.be | G43: +32 16 40 00 05 | H43: omvang niet geverifieerd
A44: Jonghof Accountants | B44: Boekhouding | C44: Klein kantoor (2-10 medewerkers) | D44: jonghof.be | E44: Brugge | F44: info@jonghof.be | G44: 050 67 82 08 | H44: sinds 2010; omvang niet geverifieerd
A45: Kantoor Rombouts | B45: Boekhouding | C45: Klein kantoor (2-10 medewerkers) | D45: kantoorrombouts.be | E45: Vilvoorde | F45: info@kantoorrombouts.be | G45: 02 252 15 40 | H45: omvang niet geverifieerd
A46: La Fiduciaire de Namur | B46: Boekhouding | C46: Klein kantoor (2-10 medewerkers) | D46: comptable-namur.be | E46: Namur | F46: info@ahfiduciaire.be | G46: 081 21 51 47 | H46: omvang niet geverifieerd
A47: Lyvema | B47: Boekhouding | C47: Klein kantoor (2-10 medewerkers) | D47: lyvema.be | E47: Genk | F47: info@lyvema.be | G47: 089 39 19 00 | H47: familiekantoor (Marc en Yves Leekens)
A48: M&P Boekhouders | B48: Boekhouding | C48: Klein kantoor (2-10 medewerkers) | D48: m-p.be | E48: Antwerpen | F48: km@m-p.be | G48: 03 237 68 81 | H48: omvang niet geverifieerd
A49: M-Advisors | B49: Boekhouding | C49: Klein kantoor (2-10 medewerkers) | D49: m-advisors.be | E49: Boom | G49: 03 808 14 40 | H49: geen publiek e-mailadres gevonden
A50: Optimus Accountancy | B50: Boekhouding | C50: Klein kantoor (2-10 medewerkers) | D50: optimus-accountancy.be | E50: Tielt | F50: info@optimus-accountancy.be | G50: 051 40 17 82 | H50: omvang niet geverifieerd
A51: Raadhuis Boekhouding & Fiscaliteit | B51: Boekhouding | C51: Klein kantoor (2-10 medewerkers) | D51: raadhuis.be | E51: Brugge (Sint-Andries) | F51: contact@raadhuis.be | G51: 050 61 17 70 | H51: ook bank & verzekeringen; omvang niet geverifieerd
A52: REFIBO | B52: Boekhouding | C52: Klein kantoor (2-10 medewerkers) | D52: refibo.be | E52: Gentbrugge | F52: info@refibo.be | G52: +32 9 223 31 54 | H52: omvang niet geverifieerd
A53: Ronny Steyaert Accountants | B53: Boekhouding | C53: Klein kantoor (2-10 medewerkers) | D53: steyaertaccountants.be | E53: Ieper | F53: info@steyaertaccountants.be | H53: omvang niet geverifieerd
A54: Snyers Accountants & Belastingconsulenten | B54: Boekhouding | C54: Klein kantoor (2-10 medewerkers) | D54: snyers.eu | E54: Paal (Beringen) | F54: info@snyers.eu | G54: +32 11 45 64 50 | H54: klein kantoor volgens zoekresultaat
A55: Sogenam | B55: Boekhouding | C55: Klein kantoor (2-10 medewerkers) | D55: sogenam.com | E55: Bouge (Namur) | F55: info@sogenam.com | G55: +32 81 21 56 62 | H55: omvang niet geverifieerd
A56: Triaccount | B56: Boekhouding | C56: Klein kantoor (2-10 medewerkers) | D56: triaccount.be | E56: Brugge | F56: info@triaccount.be | G56: +32 50 28 92 50 | H56: omvang niet geverifieerd
A57: Ulysse Finances | B57: Boekhouding | C57: Klein kantoor (2-10 medewerkers) | D57: ulysse-finances.be | E57: Oupeye | F57: patrick.lacroix@ulyssefinances.be | G57: +32 4 379 22 10 | H57: ±5 VTE; persoonlijk adres
A58: United Accountants (PIA) | B58: Boekhouding | C58: Klein kantoor (2-10 medewerkers) | D58: united-accountants.be | E58: Gent | F58: info@united-accountants.be | G58: 09 223 69 95 | H58: omvang niet geverifieerd
A59: Van Gassen Boekhouding & Fiscaliteit | B59: Boekhouding | C59: Klein kantoor (2-10 medewerkers) | D59: vangassen.be | E59: Ekeren (Antwerpen) | G59: 03 540 00 01 | H59: e-mail afgeschermd in zoekresultaat
A60: Verhamme Accountants | B60: Boekhouding | C60: Klein kantoor (2-10 medewerkers) | E60: Kortrijk | G60: 056 35 38 16 | H60: geen e-mail gevonden
A61: VP Accountants & Belastingconsulenten | B61: Boekhouding | C61: Klein kantoor (2-10 medewerkers) | D61: vpaccountants.be | E61: Keerbergen | F61: algemeen@vpaccountants.be | G61: 015 50 08 00 | H61: omvang niet geverifieerd
A62: WDV Accountantskantoor | B62: Boekhouding | C62: Klein kantoor (2-10 medewerkers) | D62: wdvacc.be | E62: Waregem | F62: info@wdvacc.be | G62: 056 60 29 51 | H62: omvang niet geverifieerd
A63: We Count | B63: Boekhouding | C63: Klein kantoor (2-10 medewerkers) | D63: we-count.be | E63: Waregem | F63: info@we-count.be | G63: 056 61 12 90 | H63: omvang niet geverifieerd
A64: Accountancy Van As | B64: Boekhouding | C64: Groter accountantskantoor (meerdere vestigingen) | D64: van-as.be | E64: Kortrijk | F64: info@van-as.be | G64: +32 56 21 89 33 | H64: Kortrijk & Roeselare
A65: Accountantsburo Lauwers | B65: Boekhouding | C65: Groter accountantskantoor (meerdere vestigingen) | D65: buro-lauwers.be | E65: Gent / Kortrijk | G65: +32 9 225 14 38 | H65: e-mail afgeschermd op website; Kortrijk: +32 56 22 40 86
A66: ACS Accountants | B66: Boekhouding | C66: Groter accountantskantoor (meerdere vestigingen) | D66: acs.be | E66: Turnhout | F66: turnhout@acs.be | G66: +32 14 42 00 61 | H66: 10 kantoren
A67: Alaska Group | B67: Boekhouding | C67: Groter accountantskantoor (meerdere vestigingen) | D67: alaska-group.eu | E67: Brugge | F67: info.brugge@alaska-group.eu | G67: +32 50 38 80 04
A68: Carbofisc | B68: Boekhouding | C68: Groter accountantskantoor (meerdere vestigingen) | D68: carbofisc.be | E68: Oostkamp / Oostende | F68: info@carbofisc.be | G68: +32 50 54 61 92 | H68: 11 medewerkers, 2 kantoren
A69: Certifisc | B69: Boekhouding | C69: Groter accountantskantoor (meerdere vestigingen) | D69: certifisc.be | E69: Zwijnaarde / Oudenaarde | F69: gent@certifisc.be | G69: 09 221 14 41 | H69: 2 kantoren
A70: Fiscontact | B70: Boekhouding | C70: Groter accountantskantoor (meerdere vestigingen) | D70: fiscontact.be | E70: Gerpinnes / Namur / Andenne | F70: v.mercier@fiscontact.be | G70: +32 71 58 95 29 | H70: 3 vestigingen; persoonlijk adres
A71: IBA Boekhouding (I.B.A. Integraal Bedrijfsadvies) | B71: Boekhouding | C71: Groter accountantskantoor (meerdere vestigingen) | D71: iba-boekhouding.be | E71: Westerlo / Zonhoven | F71: info@iba-boekhouding.be | G71: 014 59 35 55 | H71: kantoren Westerlo en Zonhoven
A72: Konsilanto | B72: Boekhouding | C72: Groter accountantskantoor (meerdere vestigingen) | D72: konsilanto.be | E72: Mortsel | G72: 03 443 75 50 | H72: team met payroll & vermogensplanning; geen algemeen e-mailadres
A73: Legia Boekhoudkantoor | B73: Boekhouding | C73: Groter accountantskantoor (meerdere vestigingen) | D73: legia-boekhoudkantoor.be | E73: Menen / Roeselare | G73: +32 56 96 03 94 | H73: 2 vestigingen; geen publiek e-mailadres gevonden
A74: Moore Belgium (Waasland) | B74: Boekhouding | C74: Groter accountantskantoor (meerdere vestigingen) | D74: moore.be | E74: Sint-Niklaas | F74: waasland@moore.be | G74: +32 3 780 75 90
A75: myfid | B75: Boekhouding | C75: Groter accountantskantoor (meerdere vestigingen) | D75: myfid.be | E75: Brussel / Charleroi | G75: +32 2 669 46 80 | H75: digitaal kantoor, meerdere steden
A76: Persona Accountants | B76: Boekhouding | C76: Groter accountantskantoor (meerdere vestigingen) | D76: persona-accountants.be | E76: Roeselare | F76: info@persona-accountants.be | G76: +32 51 57 56 00
A77: Pijcke Accountantskantoor | B77: Boekhouding | C77: Groter accountantskantoor (meerdere vestigingen) | D77: pijckeaccountantskantoor.be | E77: Sint-Truiden / Tienen | F77: pijcke.sint-truiden@pijcke.be | G77: 011 69 76 11
A78: QPS Accountants | B78: Boekhouding | C78: Groter accountantskantoor (meerdere vestigingen) | D78: qpsaccountants.be | E78: Genk / Hasselt | F78: info@qpsaccountants.be | G78: +32 89 61 10 06 | H78: ±47 medewerkers
A79: Roslar | B79: Boekhouding | C79: Groter accountantskantoor (meerdere vestigingen) | D79: roslar.be | E79: Roeselare | F79: info@roslar.be | G79: +32 51 222 777 | H79: 3 locaties
A80: SaveTax | B80: Boekhouding | C80: Groter accountantskantoor (meerdere vestigingen) | D80: savetax.be | E80: Mettet | G80: +32 81 39 63 96 | H80: 4 kantoren (Mettet, Liège, Nivelles, Grez-Doiceau)
A81: SBB Accountants & Adviseurs | B81: Boekhouding | C81: Groter accountantskantoor (meerdere vestigingen) | D81: sbb.be | E81: Leuven | F81: info@sbb.be | G81: +32 16 24 64 85 | H81: 27 kantoren
A82: THG Namur | B82: Boekhouding | C82: Groter accountantskantoor (meerdere vestigingen) | D82: thgnamur.be | E82: Erpent (Namur) | F82: info@thgnamur.be | G82: +32 81 240 200 | H82: THG-groep
A83: Titeca pro accountants & experts | B83: Boekhouding | C83: Groter accountantskantoor (meerdere vestigingen) | D83: titeca.be | E83: Roeselare | F83: kantoor.roeselare@titeca.be | G83: 051 26 82 68
A84: Vandelanotte | B84: Boekhouding | C84: Groter accountantskantoor (meerdere vestigingen) | D84: vandelanotte.be | E84: Brugge | F84: contact@vdl.be | G84: +32 56 43 80 60
A85: VCSA Tax Accountants | B85: Boekhouding | C85: Groter accountantskantoor (meerdere vestigingen) | D85: vcs-accountants.be | E85: Leuven | F85: info@vcs-accountants.be | G85: 016 56 96 96
A86: Warfid Gent | B86: Boekhouding | C86: Groter accountantskantoor (meerdere vestigingen) | D86: warfid.be | E86: Gent | F86: gent@warfid.be | G86: 09 233 23 51
A87: WKG Groep België | B87: Boekhouding | C87: Groter accountantskantoor (meerdere vestigingen) | D87: wkggroep.be | E87: Antwerpen | G87: +32 3 660 07 20 | H87: kantoren in BE & NL; geen Belgisch e-mailadres
A88: Accuria | B88: Boekhouding | C88: Sociaal secretariaat | D88: accuria.be | E88: Sint-Niklaas | G88: 03 760 15 80 | H88: grootste regionale sociaal secretariaat Vlaanderen; geen e-mail gevonden
A89: Acerta | B89: Boekhouding | C89: Sociaal secretariaat | D89: acerta.be | E89: Brussel | G89: +32 2 333 27 20 | H89: groot; geen algemeen e-mailadres gevonden
A90: Attentia | B90: Boekhouding | C90: Sociaal secretariaat | D90: attentia.be | E90: Brussel | G90: +32 2 706 78 99 | H90: groot; e-mailadres niet leesbaar in zoekresultaat
A91: Besox | B91: Boekhouding | C91: Sociaal secretariaat | D91: besox.be | E91: Knokke-Heist | F91: info@besox.be | G91: 050 67 23 30 | H91: kmo-gericht
A92: De Nationale Patroonsdienst (NATPAT) | B92: Boekhouding | C92: Sociaal secretariaat | D92: natpat.be | E92: Merksem (Antwerpen) | F92: info@natpat.be | G92: 03 640 30 10 | H92: kmo-gericht, sinds 1946
A93: Group S | B93: Boekhouding | C93: Sociaal secretariaat | D93: groups.be | E93: Brussel (17 kantoren) | G93: 02 507 15 11 | H93: ±650 medewerkers, >20.000 werkgevers; contact via formulier
A94: Liantis | B94: Boekhouding | C94: Sociaal secretariaat | D94: liantis.be | E94: Brussel (+ vele kantoren) | F94: info@liantis.be | G94: +32 2 212 22 30 | H94: groot; e-mail/tel. uit lijst sociale verzekeringsfondsen
A95: Partena Professional | B95: Boekhouding | C95: Sociaal secretariaat | D95: partena-professional.be | E95: Brussel (28 kantoren) | F95: independant@partena.be | G95: +32 2 549 79 40 | H95: groot; adres is voor zelfstandigen-afdeling
A96: SD Worx (KMO-kantoor Kortrijk) | B96: Boekhouding | C96: Sociaal secretariaat | D96: sdworx.be | E96: Kortrijk (+ kantorennetwerk) | F96: kmo.kortrijk@sdworx.com | G96: 056 24 18 31 | H96: groot sociaal secretariaat; lokaal KMO-kantoor
A97: Securex | B97: Boekhouding | C97: Sociaal secretariaat | D97: securex.be | E97: Gent (hoofdzetel) | F97: mybusiness@securex.be | G97: +32 78 05 90 10 | H97: groot
A98: Sociaal Secretariaat der Notarissen (SSN) | B98: Boekhouding | C98: Sociaal secretariaat | D98: ssn.be | E98: Brussel | F98: info@ssn.be | G98: 02 500 14 11
A99: Sodibe | B99: Boekhouding | C99: Sociaal secretariaat | D99: sodibe.be | E99: Antwerpen | F99: info@sodibe.be | G99: 03 236 68 06 | H99: erkend sociaal secretariaat
A100: Sodiwe | B100: Boekhouding | C100: Sociaal secretariaat | D100: sodiwe.be | E100: Mechelen | F100: info@sodiwe.be | G100: +32 15 65 10 10 | H100: erkend sociaal secretariaat, KMO-focus
...

Sheet Advocaten & consultancy
A1: Bedrijfsnaam | B1: Sector | C1: Subcategorie | D1: Website | E1: Plaats | F1: E-mailadres | G1: Telefoon | H1: Opmerking (omvang / verificatie)
A2: Advocaten Delagrange | B2: Advocaten & consultancy | C2: Klein advocatenkantoor (≤5) | D2: advocatendelagrange.be | E2: Kortrijk | F2: adv@advocatendelagrange.be | G2: 056 22 02 73 | H2: omvang niet geverifieerd
A3: Advocaten Opdebeeck, De Groote & Matthys | B3: Advocaten & consultancy | C3: Klein advocatenkantoor (≤5) | D3: opdebeeckadvocaten.be | E3: Gent | F3: info@opdebeeckadvocaten.be | G3: +32 9 233 67 14 | H3: bouw-, handels- & familierecht
A4: Advocatenassociatie Cooreman-Mertens | B4: Advocaten & consultancy | C4: Klein advocatenkantoor (≤5) | D4: cooremanmertens.be | E4: Zele | F4: info@cooremanmertens.be | G4: 052 44 45 10 | H4: omvang niet geverifieerd
A5: Advocatenkantoor Beele | B5: Advocaten & consultancy | C5: Klein advocatenkantoor (≤5) | D5: be-law.eu | E5: Gent | F5: info@be-law.eu | G5: +32 9 220 99 78 | H5: omvang niet geverifieerd
A6: Advocatenkantoor Brondel, Petitat & Baele | B6: Advocaten & consultancy | C6: Klein advocatenkantoor (≤5) | D6: bpb-advocaten.be | E6: Brugge | F6: contact@bpb-advocaten.be | G6: 050 33 66 03 | H6: omvang niet geverifieerd
A7: Advocatenkantoor Comitius | B7: Advocaten & consultancy | C7: Klein advocatenkantoor (≤5) | D7: comitius.be | E7: Turnhout / Vosselaar / Geel | F7: info@comitius.be | G7: +32 14 70 37 28 | H7: 2 vennoten
A8: Advocatenkantoor D'Hulster | B8: Advocaten & consultancy | C8: Klein advocatenkantoor (≤5) | D8: kantoordhulster.be | E8: Oostende | F8: info@kantoordhulster.be | G8: 059 70 96 32 | H8: 3 advocaten
A9: Advocatenkantoor Dennis Tavernier | B9: Advocaten & consultancy | C9: Klein advocatenkantoor (≤5) | D9: advocaattavernier.be | E9: Oostende | F9: dennis@advocaattavernier.be | G9: +32 59 23 98 15 | H9: persoonlijk adres
A10: Advocatenkantoor Hoet | B10: Advocaten & consultancy | C10: Klein advocatenkantoor (≤5) | D10: hoetadvocatenkantoor.be | E10: Turnhout | F10: hans.hoet@hoetadvocatenkantoor.be | G10: +32 14 41 17 22 | H10: persoonlijk adres
A11: Advocatenkantoor Lefere-Vanderhaeghe | B11: Advocaten & consultancy | C11: Klein advocatenkantoor (≤5) | D11: jvl-advocatenkantoor.be | E11: Roeselare / Sint-Martens-Latem | F11: info@jvl-advocatenkantoor.be | G11: 051 24 36 55 | H11: 2 vennoten
A12: Advocatenkantoor Mallego & Roels | B12: Advocaten & consultancy | C12: Klein advocatenkantoor (≤5) | D12: mallego-roels.be | E12: Aalst | F12: info@mallego-roels.be | G12: +32 475 67 42 79 | H12: 2 vennoten (strafrecht)
A13: Advocatenkantoor Piet Van Eeckhaut | B13: Advocaten & consultancy | C13: Klein advocatenkantoor (≤5) | D13: vaneeckhaut.be | E13: Gent | F13: info@vaneeckhaut.be | G13: 09 225 45 01
A14: Advocatenkantoor Stappers (Turnhout) | B14: Advocaten & consultancy | C14: Klein advocatenkantoor (≤5) | D14: advocaat-turnhout.be | E14: Turnhout | G14: +32 14 70 44 70 | H14: geen e-mail gevonden
A15: Advocatenkantoor Stefaan De Geeter | B15: Advocaten & consultancy | C15: Klein advocatenkantoor (≤5) | D15: degeeter-advocaten.be | E15: Kortrijk | F15: info@degeeter-advocaten.be | G15: 056 22 78 19 | H15: 5 advocaten + 1 medewerker (net boven criterium)
A16: Advocatenkantoor Van den Driessche Karen | B16: Advocaten & consultancy | C16: Klein advocatenkantoor (≤5) | D16: aalst-advocaat.be | E16: Aalst | G16: 053 70 66 41 | H16: geen e-mail gevonden
A17: Advocatenkantoor Van der Elst | B17: Advocaten & consultancy | C17: Klein advocatenkantoor (≤5) | D17: vdelst.be | E17: Aalst | F17: advocaat@vdelst.be | G17: +32 53 70 44 64
A18: Advocatenkantoor Vantyghem-Vandeputte | B18: Advocaten & consultancy | C18: Klein advocatenkantoor (≤5) | D18: vantyghem-vandeputte.be | E18: Roeselare | G18: +32 51 26 83 00 | H18: 4 advocaten; geen e-mail gevonden
A19: Advokomvest | B19: Advocaten & consultancy | C19: Klein advocatenkantoor (≤5) | D19: advokomvest.be | E19: Brugge | F19: info@advokomvest.be | G19: 050 44 00 60 | H19: omvang niet geverifieerd
A20: Advonet Leuven (Advocatenkantoor Feremans) | B20: Advocaten & consultancy | C20: Klein advocatenkantoor (≤5) | D20: advonet-leuven.be | E20: Wilsele (Leuven) | F20: leuven@advonet.be | G20: 0476 64 14 80 | H20: omvang niet geverifieerd
A21: Aves Legal | B21: Advocaten & consultancy | C21: Klein advocatenkantoor (≤5) | D21: aveslegal.be | E21: Heverlee (Leuven) | G21: 016 31 04 20 | H21: geen e-mail gevonden
A22: Beelen Advocaten | B22: Advocaten & consultancy | C22: Klein advocatenkantoor (≤5) | D22: beelen-advocaten.be | E22: Leuven | F22: bertbeelen@beelenadvocaten.be | G22: 016 31 77 10 | H22: persoonlijk adres
A23: Bollen Advocaten | B23: Advocaten & consultancy | C23: Klein advocatenkantoor (≤5) | D23: bollenadvocaten.be | E23: Leuven | G23: +32 16 23 11 13 | H23: arbeidsrecht; geen e-mail gevonden
A24: Callebaut & Van Thienen Advocaten (CVT) | B24: Advocaten & consultancy | C24: Klein advocatenkantoor (≤5) | D24: cvt-advocaten.be | E24: Erembodegem (Aalst) | F24: info@cvt-advocaten.be | G24: 053 22 90 86 | H24: omvang niet geverifieerd
A25: CEPA Advocaten | B25: Advocaten & consultancy | C25: Klein advocatenkantoor (≤5) | D25: cepa-advocaten.be | E25: Aalst | F25: info@cepa-advocaten.be | G25: +32 53 40 02 90 | H25: omvang niet geverifieerd
A26: Clavis Advocaten | B26: Advocaten & consultancy | C26: Klein advocatenkantoor (≤5) | D26: clavisadvocaten.be | E26: Leuven | F26: kristel.jansens@clavisadvocaten.be | G26: +32 16 22 24 45 | H26: kleinschalig kantoor; persoonlijk adres
A27: De Broeck Van Laere & Partners | B27: Advocaten & consultancy | C27: Klein advocatenkantoor (≤5) | D27: dvp-law.com | E27: Koekelberg | F27: secretariaat@dvp-law.com | G27: +32 2 423 00 42 | H27: omvang niet geverifieerd
A28: De Gendt Advocaten | B28: Advocaten & consultancy | C28: Klein advocatenkantoor (≤5) | D28: degendtadvocaten.be | E28: Gent | F28: info@degendtadvocaten.be | H28: omvang niet geverifieerd
A29: De Ridder, Lahousse & Partners | B29: Advocaten & consultancy | C29: Klein advocatenkantoor (≤5) | D29: deridder-law.be | E29: Mechelen | F29: advocaat@deridder-law.be | H29: geen telefoon in zoekresultaat
A30: Delbrouck & Daeninck Advocaten | B30: Advocaten & consultancy | C30: Klein advocatenkantoor (≤5) | D30: delbrouck-daeninck.be | E30: Hasselt | F30: info@delbrouck-daeninck.be | G30: 011 21 53 15 | H30: een van de grotere kantoren in Hasselt; mogelijk >5 medewerkers
A31: Devos & Van Den Eynde Advocatenassociatie | B31: Advocaten & consultancy | C31: Klein advocatenkantoor (≤5) | D31: devosvde-law.be | E31: Geel | G31: +32 14 58 55 18 | H31: full-service; geen e-mail gevonden
A32: ETHOS Advocaten | B32: Advocaten & consultancy | C32: Klein advocatenkantoor (≤5) | D32: ethosadvocaten.be | E32: Leuven | F32: info@ethosadvocaten.be | G32: 016 22 24 57
A33: Exacto Advocaten | B33: Advocaten & consultancy | C33: Klein advocatenkantoor (≤5) | D33: exacto-advocaten.be | E33: Hasselt | F33: info@exacto-advocaten.be | G33: 011 23 30 64 | H33: advocaten voor ondernemingen; omvang niet geverifieerd
A34: Forum Advocaten | B34: Advocaten & consultancy | C34: Klein advocatenkantoor (≤5) | D34: forumadvocaten.be | E34: Antwerpen | F34: info@forumadvocaten.be | G34: +32 3 369 95 65 | H34: omvang niet geverifieerd
A35: GD&A Advocaten | B35: Advocaten & consultancy | C35: Klein advocatenkantoor (≤5) | D35: gdena-advocaten.be | E35: Mechelen | F35: info@gdena-advocaten.be | G35: 015 40 49 40 | H35: omvang niet geverifieerd
A36: Heger Association | B36: Advocaten & consultancy | C36: Klein advocatenkantoor (≤5) | D36: avocatsheger.be | E36: Namur | F36: info@avocatsheger.be | G36: +32 81 23 08 13
A37: Hoefkens Advocaten | B37: Advocaten & consultancy | C37: Klein advocatenkantoor (≤5) | D37: hvdw.be | E37: Lille / Geel | F37: info@hvdw.be | G37: 0477 32 25 85
A38: HTPC Avocats | B38: Advocaten & consultancy | C38: Klein advocatenkantoor (≤5) | D38: htpc-avocats.be | E38: Jambes (Namur) | F38: info@htpc-avocats.be | G38: 081 74 42 04 | H38: 4 vennoten
A39: Koraal Advocaten & Bemiddelaars | B39: Advocaten & consultancy | C39: Klein advocatenkantoor (≤5) | D39: koraaladvocaten.com | E39: Hasselt (+ Bilzen, Tessenderlo, Maasmechelen) | F39: info@koraaladvocaten.com | G39: +32 11 25 20 20 | H39: meerdere zitdagplaatsen; mogelijk >5 medewerkers
A40: Leges | B40: Advocaten & consultancy | C40: Klein advocatenkantoor (≤5) | D40: leges.be | E40: Liège | F40: info@leges.be | G40: +32 4 344 06 60 | H40: omvang niet geverifieerd
A41: Lexcour Advocaten | B41: Advocaten & consultancy | C41: Klein advocatenkantoor (≤5) | D41: lexcour.be | E41: Kortrijk | F41: info@lexcour.be | G41: +32 56 53 35 10 | H41: omvang niet geverifieerd
A42: Litigius Avocats | B42: Advocaten & consultancy | C42: Klein advocatenkantoor (≤5) | D42: litigius.be | E42: Brussel | F42: info@litigius.be | G42: 02 428 11 83 | H42: omvang niet geverifieerd
A43: M&W Advocatenkantoor | B43: Advocaten & consultancy | C43: Klein advocatenkantoor (≤5) | D43: mw-advocatenkantoor.be | E43: Keerbergen (regio Mechelen) | G43: 015 54 00 00 | H43: geen e-mail gevonden
A44: Novalis Law | B44: Advocaten & consultancy | C44: Klein advocatenkantoor (≤5) | D44: novalis.law | E44: Brussel | F44: info@novalis.law | G44: +32 2 513 19 62 | H44: omvang niet geverifieerd
A45: Peeters Law | B45: Advocaten & consultancy | C45: Klein advocatenkantoor (≤5) | D45: peeterslaw.net | E45: Antwerpen | F45: info@peeterslaw.com | G45: +32 3 544 93 55 | H45: omvang niet geverifieerd
A46: Pure Advocaten | B46: Advocaten & consultancy | C46: Klein advocatenkantoor (≤5) | D46: pureadvocaten.be | E46: Gent | F46: info@pureadvocaten.be | G46: +32 9 222 89 19 | H46: omvang niet geverifieerd
A47: RVC Advocaten | B47: Advocaten & consultancy | C47: Klein advocatenkantoor (≤5) | D47: rvcadvocaten.be | E47: Turnhout / Antwerpen | F47: info@rvc.legal | G47: +32 14 44 80 80 | H47: 2 vennoten
A48: SOETE Advocaten | B48: Advocaten & consultancy | C48: Klein advocatenkantoor (≤5) | D48: soete-advocaten.be | E48: Oostende / Brugge | F48: kantoor@soete-advocaten.be | G48: +32 59 70 30 33 | H48: omvang niet geverifieerd
A49: Stevens & Wallace Advocaten | B49: Advocaten & consultancy | C49: Klein advocatenkantoor (≤5) | D49: stevens-wallace.be | E49: Aalst | F49: info@stevens-wallace.be | G49: 053 78 50 04 | H49: omvang niet geverifieerd
A50: Talo Advocaten | B50: Advocaten & consultancy | C50: Klein advocatenkantoor (≤5) | D50: taloadvocaten.be | E50: Antwerpen | F50: info@taloadvocaten.be | G50: 03 612 57 60 | H50: omvang niet geverifieerd
A51: Tritsmans Advocaten | B51: Advocaten & consultancy | C51: Klein advocatenkantoor (≤5) | D51: tritsmans.com | E51: Antwerpen | F51: advocaten@kantoortritsmans.com | G51: +32 3 244 11 20 | H51: omvang niet geverifieerd
A52: TVO Advocaten | B52: Advocaten & consultancy | C52: Klein advocatenkantoor (≤5) | D52: tvo-advocaten.be | E52: Hasselt | F52: info@tvo-advocaten.be | H52: omvang niet geverifieerd
A53: VHL Advocaten | B53: Advocaten & consultancy | C53: Klein advocatenkantoor (≤5) | D53: vhl-advocaten.be | E53: Mechelen | G53: 015 34 35 97 | H53: geen e-mail gevonden
A54: Blontrock & Vermeersch, geassocieerde notarissen | B54: Advocaten & consultancy | C54: Notariskantoor | D54: blontrock-vermeersch.be | E54: Brugge | F54: notariaat@blontrock-vermeersch.be | G54: 050 44 05 40
A55: Bosmans, Distelmans & Vanherle | B55: Advocaten & consultancy | C55: Notariskantoor | D55: notabd.be | E55: Leuven | F55: info@notabd.be | G55: 016 31 65 30 | H55: 3 notarissen
A56: Bossuyt & Lecluyse Notarisvennootschap | B56: Advocaten & consultancy | C56: Notariskantoor | D56: notbossuytlecluyse.be | E56: Brugge | F56: info@notbossuytlecluyse.be | G56: 050 33 49 17
A57: Cops & Swenters, geassocieerde notarissen | B57: Advocaten & consultancy | C57: Notariskantoor | D57: csnotarissen.be | E57: Maaseik / Dilsen-Stokkem | F57: info@csnotarissen.be | G57: 089 56 90 50
A58: De Paepe & Verhoeve, geassocieerde notarissen | B58: Advocaten & consultancy | C58: Notariskantoor | D58: notariaat14.be | E58: Gent | F58: info@notariaat14.be | G58: 09 225 29 94
A59: Deckers Notarissen | B59: Advocaten & consultancy | C59: Notariskantoor | D59: deckersnotarissen.be | E59: Antwerpen | F59: info@deckersnotarissen.be | G59: +32 3 233 76 33
A60: DELTA Notarissen | B60: Advocaten & consultancy | C60: Notariskantoor | D60: deltanotarissen.be | E60: Hasselt / Sint-Truiden | F60: info@deltanotarissen.be | G60: 011 15 33 33 | H60: 2 kantoren
A61: Flemings, Jansen & Co, geassocieerde notarissen | B61: Advocaten & consultancy | C61: Notariskantoor | D61: fjnot.be | E61: Lommel | F61: info@fjnot.be | G61: +32 11 54 40 19 | H61: 3 notarissen
A62: Jansen, Wallays & De Meutter | B62: Advocaten & consultancy | C62: Notariskantoor | D62: notarissen-vaart.be | E62: Leuven | F62: notaris@notarissen-vaart.be | G62: 016 24 11 90
A63: Lemey, Van Haverbeke & Brysse | B63: Advocaten & consultancy | C63: Notariskantoor | D63: lvhb-notarissen.be | E63: Gent | G63: 09 223 42 57 | H63: geen e-mail gevonden
A64: M&V Notaires Associés | B64: Advocaten & consultancy | C64: Notariskantoor | D64: mvnot.be | E64: Charleroi | F64: jeanphilippe.matagne@belnot.be | G64: 071 32 07 25 | H64: persoonlijk adres notaris
A65: NOTA | B65: Advocaten & consultancy | C65: Notariskantoor | D65: nota.be | E65: Antwerpen | F65: info@nota.be | G65: 03 470 28 00
A66: NOTABIS Notaires | B66: Advocaten & consultancy | C66: Notariskantoor | D66: notabis.be | E66: Liège | F66: info@notabis.be | G66: +32 4 220 16 16
A67: NOTABLINK | B67: Advocaten & consultancy | C67: Notariskantoor | D67: notablink.be | E67: Leuven | F67: info@notablink.be | G67: 016 36 20 00
A68: Notaire Caroline Draguet | B68: Advocaten & consultancy | C68: Notariskantoor | D68: notairedraguet.be | E68: Monceau-sur-Sambre (Charleroi) | F68: caroline.draguet@notaire.be | G68: 071 32 15 59 | H68: persoonlijk adres notaris
A69: Notaire Sophie Lefevre | B69: Advocaten & consultancy | C69: Notariskantoor | D69: notairesophielefevre.be | E69: Mont-sur-Marchienne (Charleroi) | F69: sophie.lefevre@belnot.be | G69: 071 36 16 70 | H69: persoonlijk adres notaris
A70: Notaires Dupuis et Associés | B70: Advocaten & consultancy | C70: Notariskantoor | D70: notairesdupuis.be | E70: Charleroi | F70: etude@notairesdupuis.be | G70: 071 35 35 15
A71: Notaris Anne Cartuyvels | B71: Advocaten & consultancy | C71: Notariskantoor | D71: notariscartuyvels.be | E71: Antwerpen | F71: info@notariscartuyvels.be | G71: 03 238 45 35
A72: Notaris Joost Eeman | B72: Advocaten & consultancy | C72: Notariskantoor | D72: notariseeman.be | E72: Gent | F72: joost.eeman@notaris.be | G72: 09 241 80 60 | H72: persoonlijk adres notaris
A73: Notariskantoor Huygens & Lefevre | B73: Advocaten & consultancy | C73: Notariskantoor | D73: notarissenveemarkt.be | E73: Mechelen | F73: info@notarissenveemarkt.be | G73: +32 15 28 75 40
A74: Notarissen Celis & Liesse | B74: Advocaten & consultancy | C74: Notariskantoor | D74: notaris-celis.be | E74: Antwerpen | F74: info@notaris-celis.be | G74: 03 213 86 00
A75: Notarissen Lauranne Rooman & An Berghmans | B75: Advocaten & consultancy | C75: Notariskantoor | D75: rooman-berghmans.be | E75: Leuven | F75: lauranne.rooman@belnot.be | G75: 016 22 16 87 | H75: persoonlijk adres notaris
A76: Notas geassocieerde notarissen | B76: Advocaten & consultancy | C76: Notariskantoor | D76: notasgent.be | E76: Gent | F76: info@notas.be | G76: 09 225 60 60
A77: Raes & Van Hamme Notarissen | B77: Advocaten & consultancy | C77: Notariskantoor | D77: rvh-notarissen.be | E77: Gent | F77: info@rvh-notarissen.be | G77: 09 225 72 88
A78: Société Notariale Frédéric Duchateau | B78: Advocaten & consultancy | C78: Notariskantoor | D78: notaire-duchateau.be | E78: Namur | F78: etude@notaire-duchateau.be | G78: 081 22 00 72
A79: SZABO Notarissen | B79: Advocaten & consultancy | C79: Notariskantoor | D79: szabonotarissen.be | E79: Turnhout | F79: info@szabonotarissen.be | G79: +32 14 41 19 87
A80: West, geassocieerde notarissen | B80: Advocaten & consultancy | C80: Notariskantoor | D80: westnotarissen.be | E80: Kortrijk / Koksijde | F80: koksijde@westnotarissen.be | H80: telefoon niet volledig in zoekresultaat
A81: Étude Notariale Thierry Lannoy | B81: Advocaten & consultancy | C81: Notariskantoor | D81: notairelannoy.be | E81: Charleroi | G81: 071 32 05 04 | H81: geen e-mail gevonden
A82: A Priori | B82: Advocaten & consultancy | C82: Bedrijfsadvies / HR-consultancy | D82: apriori.be | E82: Aarschot / Antwerpen | F82: info@apriori.be | G82: +32 470 70 70 25 | H82: selectie- & personeelsadvies
A83: Agyss | B83: Advocaten & consultancy | C83: Bedrijfsadvies / HR-consultancy | D83: agyss.be | E83: Sint-Denijs-Westrem (Gent) | G83: +32 9 387 01 79 | H83: direct search & HR-consultancy; e-mail afgeschermd
A84: Allianz KMO Consulting | B84: Advocaten & consultancy | C84: Bedrijfsadvies / HR-consultancy | D84: allianz-kmoconsult.be | E84: Wilrijk (Antwerpen) | F84: office@allianz-kmoconsult.be | G84: 03 827 64 21 | H84: kmo-consultancy, 25 jaar
A85: Ascento (Agilitas Group) | B85: Advocaten & consultancy | C85: Bedrijfsadvies / HR-consultancy | D85: ascento.be | E85: Mechelen | F85: info@ascento.be | G85: +32 2 302 20 43 | H85: HR-consultancy
A86: Dendooven Consulting | B86: Advocaten & consultancy | C86: Bedrijfsadvies / HR-consultancy | D86: dendoovenconsulting.be | E86: Tielt | F86: ilse@dendoovenconsulting.be | G86: 051 24 76 83 | H86: M&A-begeleiding & financieel advies; persoonlijk adres
A87: HR voor KMO's | B87: Advocaten & consultancy | C87: Bedrijfsadvies / HR-consultancy | D87: hrvoorkmos.be | E87: Haacht | F87: info@hrvoorkmos.be | G87: 0477 20 37 31 | H87: HR-advies & rekrutering voor kmo's
A88: IDEA Consult | B88: Advocaten & consultancy | C88: Bedrijfsadvies / HR-consultancy | D88: ideaconsult.be | E88: Brussel | F88: info@ideaconsult.be | G88: +32 2 282 17 10 | H88: beleidsadvies
A89: MENS | B89: Advocaten & consultancy | C89: Bedrijfsadvies / HR-consultancy | D89: mens.be | E89: Kortrijk | F89: vraaghet@mens.be | G89: 056 25 51 23 | H89: HR-outsourcing, advies en opleidingen; omvang niet geverifieerd
A90: MG Consultants | B90: Advocaten & consultancy | C90: Bedrijfsadvies / HR-consultancy | D90: mgconsultants.be | E90: Provincie Namur | G90: +32 83 61 36 00 | H90: HR-consultancy; geen e-mail gevonden
A91: Move HR | B91: Advocaten & consultancy | C91: Bedrijfsadvies / HR-consultancy | D91: movehr.be | E91: Hasselt | F91: robby@movehr.be | G91: 0476 62 55 77 | H91: HR voor kmo's; persoonlijk adres
A92: Multiple Choice Belgium | B92: Advocaten & consultancy | C92: Bedrijfsadvies / HR-consultancy | D92: multiplechoice.be | E92: Brasschaat | F92: info@multiplechoice.be | G92: +32 473 30 02 18 | H92: kmo-advies & overnamebemiddeling
A93: Orpsy | B93: Advocaten & consultancy | C93: Bedrijfsadvies / HR-consultancy | D93: orpsy.be | E93: Gent / Antwerpen | F93: info@orpsy.be | G93: +32 9 224 18 57 | H93: assessment & executive search, >35 jaar
A94: PointHR | B94: Advocaten & consultancy | C94: Bedrijfsadvies / HR-consultancy | D94: pointhr.be | E94: Oost-Vlaanderen | G94: 09 396 90 00 | H94: 100% focus op KMO's; geen publiek e-mailadres gevonden
A95: Probis | B95: Advocaten & consultancy | C95: Bedrijfsadvies / HR-consultancy | D95: probis.be | E95: Geel | F95: info@probis.be | G95: +32 14 58 58 00
A96: Puur HR | B96: Advocaten & consultancy | C96: Bedrijfsadvies / HR-consultancy | D96: puurhr.be | E96: Kortrijk | F96: hello@puurhr.be | G96: 0475 45 29 90 | H96: recrutering, employer branding, HR-consultancy voor KMO's
A97: SCV Limburg (Senior Consultants Vlaanderen) | B97: Advocaten & consultancy | C97: Bedrijfsadvies / HR-consultancy | D97: consulting-scvlimburg.be | E97: Hasselt | F97: limburg@seniorconsultantsvlaanderen.be | G97: 0475 63 64 59 | H97: vzw van ex-managers; KMO-portefeuille erkend
A98: Simplify HR | B98: Advocaten & consultancy | C98: Bedrijfsadvies / HR-consultancy | D98: simplify-hr.be | E98: Limburg | F98: info@simplify-hr.be | G98: 011 10 01 92 | H98: HR-consultancy, payroll & selectie
A99: Straff HR Consultancy | B99: Advocaten & consultancy | C99: Bedrijfsadvies / HR-consultancy | D99: straff.be | E99: België | F99: thomas@straff.be | G99: +32 475 78 19 23 | H99: persoonlijk adres
A100: Vanpoucke Consulting | B100: Advocaten & consultancy | C100: Bedrijfsadvies / HR-consultancy | D100: vanpouckeconsulting.be | E100: West-Vlaanderen | F100: info@vanpouckeconsulting.be | G100: +32 478 78 04 57 | H100: organisatie- en personeelsadvies voor KMO's
...

Sheet Transport & logistiek
A1: Bedrijfsnaam | B1: Sector | C1: Subcategorie | D1: Website | E1: Plaats | F1: E-mailadres | G1: Telefoon | H1: Opmerking (omvang / verificatie)
A2: B.B. Trans | B2: Transport & logistiek | C2: Transportbedrijf (eigen wagenpark) | D2: bbtrans.be | E2: Holsbeek | G2: 016 56 38 59 | H2: koel- & expresstransport; geen e-mail gevonden
A3: Benelux Trans | B3: Transport & logistiek | C3: Transportbedrijf (eigen wagenpark) | D3: beneluxtrans.be | E3: Groot-Bijgaarden (Dilbeek) | G3: +32 2 463 51 51 | H3: familiebedrijf sinds 1928, koeltransport; mogelijk >40 werknemers; contact via formulier
A4: Bevertrans | B4: Transport & logistiek | C4: Transportbedrijf (eigen wagenpark) | D4: bevertrans.be | E4: Veldegem (Zedelgem) | F4: info@bevertrans.be | G4: +32 50 28 99 69 | H4: tankcontainer- en kippertransport; omvang niet geverifieerd
A5: Danny Trans | B5: Transport & logistiek | C5: Transportbedrijf (eigen wagenpark) | D5: dannytrans.be | E5: Bilzen | F5: danny.trans@skynet.be | G5: +32 11 33 30 35 | H5: distributie, express & kraantransport
A6: De Nobele Transport | B6: Transport & logistiek | C6: Transportbedrijf (eigen wagenpark) | D6: denobeletransport.be | E6: Lubbeek | F6: de_nobele_transport@hotmail.be | G6: 0471 24 64 54
A7: Demunster Depannage & Transport | B7: Transport & logistiek | C7: Transportbedrijf (eigen wagenpark) | D7: depannagedemunster.be | E7: Zwevegem | F7: move@demunster.be | G7: +32 56 25 89 25 | H7: takeldienst & machinetransport sinds 1989
A8: Desimpel Trans | B8: Transport & logistiek | C8: Transportbedrijf (eigen wagenpark) | D8: desimpel-trans.be | E8: Ichtegem | G8: +32 51 58 06 44 | H8: kipper- en tractievervoer; contact via formulier
A9: Distributie Govaerts | B9: Transport & logistiek | C9: Transportbedrijf (eigen wagenpark) | D9: distributiegovaerts.be | E9: Kortessem | F9: info@distributiegovaerts.be | G9: +32 477 30 13 45 | H9: sinds 1997; 24/7
A10: E.T.L. European Transport & Logistics | B10: Transport & logistiek | C10: Transportbedrijf (eigen wagenpark) | D10: etltransport.be | E10: Genk | F10: info@etltransport.be | G10: +32 89 84 11 22 | H10: sinds 1992
A11: GOBO Transport & Logistics | B11: Transport & logistiek | C11: Transportbedrijf (eigen wagenpark) | D11: gobo.eu | E11: Lanaken | F11: info@gobo.eu | G11: +32 89 71 00 70 | H11: familiebedrijf sinds 1963; mogelijk >40 werknemers
A12: Heeze Transport Logistiek Belgium | B12: Transport & logistiek | C12: Transportbedrijf (eigen wagenpark) | E12: Lochristi | G12: +32 9 355 60 98 | H12: geen e-mail gevonden
A13: Internationaal Transport Gilbert De Clercq | B13: Transport & logistiek | C13: Transportbedrijf (eigen wagenpark) | D13: gilbertdeclercq.com | E13: Temse / Sint-Niklaas | F13: info@gilbertdeclercq.com | G13: +32 3 775 74 26 | H13: familiebedrijf sinds 1957; mogelijk >40 werknemers
A14: K & E Trucking (Cool Traffic) | B14: Transport & logistiek | C14: Transportbedrijf (eigen wagenpark) | D14: cooltraffic.be | E14: Oudenaarde | F14: info@ke-trucking.com | G14: +32 55 45 79 01 | H14: ±60 koeltransporteenheden; mogelijk >40 werknemers
A15: KMS & CO | B15: Transport & logistiek | C15: Transportbedrijf (eigen wagenpark) | D15: kms-co.be | E15: Meise | F15: info@kms-co.be | G15: 0484 02 89 98 | H15: pakket- & goederentransport
A16: KTS Transport | B16: Transport & logistiek | C16: Transportbedrijf (eigen wagenpark) | D16: kts-bvba.com | E16: Wilrijk (Antwerpen) | F16: info@kts-bvba.com | G16: +32 3 770 79 09 | H16: container- & goederentransport
A17: LD Trans | B17: Transport & logistiek | C17: Transportbedrijf (eigen wagenpark) | D17: ld-trans.be | E17: Kortessem | F17: ld-trans@outlook.be | G17: +32 12 74 40 57 | H17: transport & opslag, sinds 2005
A18: Mervielde | B18: Transport & logistiek | C18: Transportbedrijf (eigen wagenpark) | D18: mervielde.be | E18: Ertvelde (Evergem) | F18: transport@mervielde.be | G18: +32 9 341 96 96 | H18: tanktransport; mogelijk >40 werknemers
A19: Nieuwenhuyse | B19: Transport & logistiek | C19: Transportbedrijf (eigen wagenpark) | D19: nieuwenhuyse.be | E19: Moen (Zwevegem) | F19: info@nieuwenhuyse.be | G19: 056 75 51 00 | H19: Goederenvervoer Benelux sinds 1953
A20: NV Transport De Vreese | B20: Transport & logistiek | C20: Transportbedrijf (eigen wagenpark) | D20: devreesetransport.be | E20: Oostakker (Gent) | F20: geert@devreesetransport.be | G20: 09 252 27 37 | H20: persoonlijk adres zaakvoerder; kraan-/diepladertransport
A21: Peethultra Transport | B21: Transport & logistiek | C21: Transportbedrijf (eigen wagenpark) | D21: peethultra.be | E21: Westmalle (Malle) | F21: info@peethultra.be | G21: 03 312 05 31 | H21: gerechtelijke reorganisatie afgesloten sept. 2025 — status nakijken
A22: S'Jegers Transport | B22: Transport & logistiek | C22: Transportbedrijf (eigen wagenpark) | D22: sjegers.eu | E22: Laakdal | F22: info@sjegers.eu | G22: +32 13 67 78 23 | H22: mogelijk >40 werknemers
A23: Toco-Trans | B23: Transport & logistiek | C23: Transportbedrijf (eigen wagenpark) | D23: toco-trans.be | E23: Grembergen (Dendermonde) | G23: +32 478 74 40 71 | H23: gsm zaakvoerder; geen e-mail gevonden
A24: Trans Alleman | B24: Transport & logistiek | C24: Transportbedrijf (eigen wagenpark) | D24: transalleman.be | E24: Geluwe (Wervik) | H24: milieutransport (o.a. voor Vanheede); contact via website
A25: Transport De Laet | B25: Transport & logistiek | C25: Transportbedrijf (eigen wagenpark) | D25: transportdelaet.wordpress.com | E25: Elewijt (Zemst) | G25: 015 61 13 51 | H25: tanktransport; geen e-mail gevonden
A26: Transport De Sauter | B26: Transport & logistiek | C26: Transportbedrijf (eigen wagenpark) | D26: desauter.be | E26: Brugge | G26: +32 50 31 81 41 | H26: familiebedrijf; geen e-mail gevonden
A27: Transport Demyttenaere & Co | B27: Transport & logistiek | C27: Transportbedrijf (eigen wagenpark) | D27: transportdemyttenaere.be | E27: Rumbeke (Roeselare) | F27: info@transportdemyttenaere.be | G27: +32 51 25 16 03 | H27: sinds 1971
A28: Transport Fransen J. | B28: Transport & logistiek | C28: Transportbedrijf (eigen wagenpark) | E28: Putte | G28: +32 15 73 09 04 | H28: familiebedrijf, 60+ jaar; sinds 2024 overgenomen door Corneel Geerts; geen publiek e-mailadres gevonden
A29: Transport Kris De Leeneer | B29: Transport & logistiek | C29: Transportbedrijf (eigen wagenpark) | E29: Lokeren | G29: +32 52 35 43 10 | H29: geen e-mail gevonden
A30: Transport Macharis | B30: Transport & logistiek | C30: Transportbedrijf (eigen wagenpark) | D30: transport-macharis.be | E30: Dendermonde | F30: info@transport-macharis.be | G30: +32 52 21 17 49 | H30: familiebedrijf
A31: Transport Miquel Declercq | B31: Transport & logistiek | C31: Transportbedrijf (eigen wagenpark) | D31: transport-miquel-declercq.be | E31: Harelbeke | G31: 0494 15 56 45 | H31: geen e-mail gevonden; omvang niet geverifieerd
A32: Transport Roosens | B32: Transport & logistiek | C32: Transportbedrijf (eigen wagenpark) | D32: roosens.be | E32: Haasdonk (Beveren) | F32: roosens@roosens.be | G32: +32 3 775 01 01 | H32: container-/tanktransport; mogelijk >40 werknemers
A33: Transport Stekelorum | B33: Transport & logistiek | C33: Transportbedrijf (eigen wagenpark) | D33: transportstekelorum.be | E33: Vleteren (Oostvleteren) | F33: info@stekelorumtransport.be | G33: 057 40 01 82 | H33: ±25 vrachtwagens; familiebedrijf
A34: Transport Van de Velde | B34: Transport & logistiek | C34: Transportbedrijf (eigen wagenpark) | D34: transportvandevelde.be | E34: Wetteren | F34: info@transportvandevelde.be | G34: +32 9 252 12 25
A35: Transport Van Heesvelde | B35: Transport & logistiek | C35: Transportbedrijf (eigen wagenpark) | D35: mervielde.be | E35: Ertvelde (Evergem) | F35: transport@van-heesvelde.be | G35: +32 9 341 96 80 | H35: zusterbedrijf van Mervielde
A36: Transport Van Renterghem | B36: Transport & logistiek | C36: Transportbedrijf (eigen wagenpark) | D36: trans-tvr.be | E36: Deinze | F36: info@trans-tvr.be | G36: 09 387 00 57 | H36: familiebedrijf, volle ladingen
A37: Transport Verbeken | B37: Transport & logistiek | C37: Transportbedrijf (eigen wagenpark) | D37: verbekentrans.be | E37: Dendermonde | F37: info@verbekentrans.be | G37: +32 52 21 68 16 | H37: Vloeibare voeding, sinds 1965
A38: Transport W. Franssens | B38: Transport & logistiek | C38: Transportbedrijf (eigen wagenpark) | E38: Verrebroek (Beveren) | G38: +32 3 789 30 41 | H38: geen e-mail gevonden
A39: Travadri | B39: Transport & logistiek | C39: Transportbedrijf (eigen wagenpark) | D39: travadri.com | E39: Merelbeke | G39: 09 230 42 33 | H39: groupage België–Frankrijk; geen e-mail gevonden
A40: Trippaers Transport | B40: Transport & logistiek | C40: Transportbedrijf (eigen wagenpark) | D40: trippaers.com | E40: Genk | G40: +32 89 35 66 00 | H40: geen e-mail gevonden
A41: V1000 Explendid Cargo Transport | B41: Transport & logistiek | C41: Transportbedrijf (eigen wagenpark) | D41: v1000.be | E41: Roeselare | F41: info@v1000.be | G41: +32 51 24 29 91 | H41: Benelux-transport
A42: Vulsteke | B42: Transport & logistiek | C42: Transportbedrijf (eigen wagenpark) | D42: vulstekebvba.be | E42: Kortemark | F42: info@vulstekebvba.be | G42: 051 56 85 80 | H42: containerdienst & transport, familiebedrijf
A43: Willems | B43: Transport & logistiek | C43: Transportbedrijf (eigen wagenpark) | D43: willems-zout.be | E43: Vorselaar | F43: info@willems-zout.be | G43: +32 14 25 85 70 | H43: familiebedrijf; kippers, platte wagens, kraanwagens
A44: Antwerp City Express | B44: Transport & logistiek | C44: Koeriersbedrijf | D44: antwerpcityexpress.be | E44: Antwerpen | F44: info@antwerpcityexpress.be | G44: +32 3 230 20 30 | H44: Antwerpen & Brussel
A45: Antwerp Sprint Service | B45: Transport & logistiek | C45: Koeriersbedrijf | D45: antwerpsprintservice.be | E45: Hemiksem | F45: antwerpsprintservice@skynet.be | G45: +32 3 322 06 01 | H45: 24/7 spoedkoerier
A46: ATC Lauwe | B46: Transport & logistiek | C46: Koeriersbedrijf | D46: atc-lauwe.be | E46: Lauwe (Menen) | F46: info@atc-lauwe.be | G46: 0475 34 95 92 | H46: gsm-nummer; omvang niet geverifieerd
A47: BCS Belgium | B47: Transport & logistiek | C47: Koeriersbedrijf | D47: bcs-belgium.be | E47: Brussel (Sint-Jans-Molenbeek) | F47: info@bcsbelgium.com | G47: 02 886 08 20 | H47: >10 jaar expresvervoer
A48: Bulbul Group | B48: Transport & logistiek | C48: Koeriersbedrijf | D48: bulbulgroup.be | E48: Jemeppe-sur-Meuse (Liège) | F48: societe@bulbulgroup.be | G48: 0471 89 37 06 | H48: express & distributie
A49: D&L Deliveries & Logistics | B49: Transport & logistiek | C49: Koeriersbedrijf | D49: dxl.be | E49: Hasselt | G49: 011 27 26 15 | H49: geen e-mail gevonden
A50: DB-Express | B50: Transport & logistiek | C50: Koeriersbedrijf | D50: db-express.eu | E50: Izegem | F50: info@db-express.eu | G50: 0476 89 01 71 | H50: 24/7 sneltransport
A51: Express Koerier Thierry Lenssens | B51: Transport & logistiek | C51: Koeriersbedrijf | D51: expresskoeriergent.be | E51: Zwijnaarde (Gent) | G51: 0475 46 68 78 | H51: sinds 1991; geen e-mail gevonden
A52: Express Koerier Van De Velde | B52: Transport & logistiek | C52: Koeriersbedrijf | D52: expresskoerier.be | E52: Lovendegem | F52: info@expresskoerier.be | G52: 0800 93 541
A53: Gent-Express | B53: Transport & logistiek | C53: Koeriersbedrijf | D53: gent-express.be | E53: Zwijnaarde (Gent) | F53: info@gent-express.be | G53: 09 222 64 25 | H53: koerier en lijndiensten; omvang niet geverifieerd
A54: Gocaps Express | B54: Transport & logistiek | C54: Koeriersbedrijf | D54: gocaps.be | E54: Zaventem | F54: gocapsexpress@gmail.com | G54: +32 475 30 77 32 | H54: kleinschalig; waarschijnlijk <10 werknemers
A55: Kempen Transport | B55: Transport & logistiek | C55: Koeriersbedrijf | D55: kempentransport.be | E55: Kempen (BE/NL) | F55: info@kempentransport.be | G55: +32 14 75 43 91
A56: Koerierdienst Antwerpen | B56: Transport & logistiek | C56: Koeriersbedrijf | D56: koerierdienstantwerpen.be | E56: Brasschaat / Wommelgem | F56: info@koerierdienstantwerpen.be | G56: 0478 82 39 53 | H56: omvang niet geverifieerd
A57: KoerierDirect | B57: Transport & logistiek | C57: Koeriersbedrijf | D57: koerierdirect.be | E57: Hasselt (centrale planning) | G57: 0492 47 73 97 | H57: 24/7; geen e-mail gevonden
A58: KSKoerier (Kempische Sneldienst Koerier) | B58: Transport & logistiek | C58: Koeriersbedrijf | D58: kskoerier.be | E58: Retie | G58: 0474 84 45 88 | H58: 24/7; geen publiek e-mailadres gevonden
A59: Kurutrans | B59: Transport & logistiek | C59: Koeriersbedrijf | D59: kurutrans.be | E59: Gent | F59: info@kurutrans.be | G59: +32 484 56 40 66 | H59: koerier & transport; omvang niet geverifieerd
A60: Lenaers Express | B60: Transport & logistiek | C60: Koeriersbedrijf | D60: lenaersexpress.be | E60: Genk | F60: info@lenaersexpress.be | G60: 089 49 13 55 | H60: nationaal & internationaal expresvervoer
A61: Morvan | B61: Transport & logistiek | C61: Koeriersbedrijf | E61: Etterbeek (Brussel) | G61: +32 2 732 82 00 | H61: website en e-mail niet vermeld
A62: PTQ Transport | B62: Transport & logistiek | C62: Koeriersbedrijf | D62: ptq-trans.be | E62: België | F62: info@ptq-trans.be | G62: 0460 94 99 09 | H62: express-, kunst- & white-glove-transport
A63: Rush Express | B63: Transport & logistiek | C63: Koeriersbedrijf | D63: rush-express.be | E63: Merelbeke | G63: 0800 93 541 | H63: gratis nummer; geen e-mail gevonden
A64: Sitex Logistics | B64: Transport & logistiek | C64: Koeriersbedrijf | D64: sitexlogistics.be | E64: Antwerpen (Wilrijk) | F64: info@sitexlogistics.be | G64: +32 3 440 90 48 | H64: sprint- en expresstransport 24/7; omvang niet geverifieerd
A65: Abbeloos-Socquet | B65: Transport & logistiek | C65: Verhuisfirma | D65: abbeloos-socquet.be | E65: Brussel (Jette) | F65: info@abbeloos-socquet.be | G65: +32 2 479 41 44
A66: Adrien et Fils | B66: Transport & logistiek | C66: Verhuisfirma | D66: adrienfils.com | E66: Etterbeek (Brussel) | F66: info@adrienfils.com | G66: +32 2 734 13 27 | H66: sinds 1930; ±2000 verhuizingen/jaar
A67: Aksoy Verhuizingen | B67: Transport & logistiek | C67: Verhuisfirma | D67: aksoyverhuizingen.com | E67: Genk | G67: 0486 77 42 48 | H67: geen e-mail gevonden
A68: Anthonissen Verhuizingen | B68: Transport & logistiek | C68: Verhuisfirma | D68: wijverhuizen.be | E68: Mortsel | G68: 03 440 11 00 | H68: geen e-mail gevonden; familiebedrijf 4e generatie
A69: Antwerp Move | B69: Transport & logistiek | C69: Verhuisfirma | D69: antwerpmove.be | E69: Antwerpen | G69: 0485 64 16 26 | H69: ladderlift & verhuis; omvang niet geverifieerd
A70: Couvreur Verhuizingen | B70: Transport & logistiek | C70: Verhuisfirma | D70: couvreur-verhuizingen.be | E70: Roeselare | F70: info@couvreur-transport.be | G70: 051 22 78 22
A71: DAC Verhuizingen | B71: Transport & logistiek | C71: Verhuisfirma | D71: dacnv.be | E71: Hasselt | F71: info@dacnv.be | G71: 011 60 63 43 | H71: >2000 klanten/jaar
A72: De Beste Verhuizer | B72: Transport & logistiek | C72: Verhuisfirma | E72: Beringen | G72: 013 48 08 78 | H72: geen e-mail gevonden
A73: De Roeck Rental & Moving | B73: Transport & logistiek | C73: Verhuisfirma | D73: deroeck.be | E73: Antwerpen / Aartselaar | F73: info@deroeck.be | G73: 03 546 73 63 | H73: 2 vestigingen
A74: De Vic Verhuizingen | B74: Transport & logistiek | C74: Verhuisfirma | D74: devic.be | E74: Aartselaar | F74: info@devic.be | G74: 03 830 10 00 | H74: verhuis, lift, meubelbewaring
A75: Dockx Movers | B75: Transport & logistiek | C75: Verhuisfirma | D75: dockx-movers.be | E75: Wilrijk / Gent / Herent / Drogenbos | F75: sales@dockx-movers.be | G75: +32 3 827 30 30 | H75: familiebedrijf; waarschijnlijk >40 werknemers
A76: DVH Verhuizingen | B76: Transport & logistiek | C76: Verhuisfirma | D76: dvhverhuizingen.be | E76: Deerlijk / Kortrijk | G76: 0495 53 01 07 | H76: erkend verhuizer; e-mail afgeschermd
A77: Déménagement Breuse | B77: Transport & logistiek | C77: Verhuisfirma | D77: demenagementbreuse.com | E77: Andenne | F77: demenagementbreuse@gmail.com | G77: 0495 42 29 33 | H77: omvang niet geverifieerd
A78: Déménagement Gérard & Fils | B78: Transport & logistiek | C78: Verhuisfirma | D78: demenagementgerardetfils.be | E78: Brussel | G78: +32 2 215 08 46 | H78: e-mail afgeschermd
A79: Déménagements Pierson | B79: Transport & logistiek | C79: Verhuisfirma | D79: sprlpierson.com | E79: Andenne | F79: info@sprlpierson.com | G79: 085 84 34 41
A80: Fossoul J & Fils | B80: Transport & logistiek | C80: Verhuisfirma | D80: fossoul.be | E80: Grâce-Hollogne (Liège) | F80: info@fossoul.be | G80: +32 4 239 08 08 | H80: antennes Brussel, Namur, Verviers, Waremme
A81: Golift | B81: Transport & logistiek | C81: Verhuisfirma | D81: golift.be | E81: Manage | F81: info@golift.be | G81: 0498 59 05 08 | H81: actief in heel Wallonië
A82: Grimbergs Verhuisbedrijf | B82: Transport & logistiek | C82: Verhuisfirma | D82: grimbergsverhuisbedrijf.be | E82: Grimbergen | F82: info@grimbergsverhuisbedrijf.be | G82: 02 251 29 00 | H82: nationaal & internationaal
A83: Kristof Vervaet Verhuizingen | B83: Transport & logistiek | C83: Verhuisfirma | D83: kristofvervaet-verhuizingen.be | E83: Assenede | F83: info@kristofvervaet-verhuizingen.be | G83: +32 9 219 94 24
A84: Lift et Vous | B84: Transport & logistiek | C84: Verhuisfirma | D84: liftetvous.be | E84: Provincie Namur | G84: 0495 16 19 19 | H84: lift & verhuis; geen e-mail gevonden
A85: Louis Verhuizingen | B85: Transport & logistiek | C85: Verhuisfirma | D85: louis-verhuizingen.be | E85: Sint-Truiden | F85: info@louis-verhuizingen.be | G85: 011 69 20 77 | H85: kantoren Sint-Truiden, Genk, Tongeren
A86: Mechels Verhuisbedrijf | B86: Transport & logistiek | C86: Verhuisfirma | D86: verhuisbedrijf.be | E86: Bonheiden | F86: info@verhuisbedrijf.be | G86: +32 15 62 33 00
A87: P. Scholts & Associés | B87: Transport & logistiek | C87: Verhuisfirma | D87: scholts.be | E87: Elsene (Brussel) | F87: info@scholts.be | G87: 02 731 11 39 | H87: 4 generaties
A88: Ricky-Trans | B88: Transport & logistiek | C88: Verhuisfirma | D88: rickytrans.be | E88: Fernelmont (Namur) | F88: info@rickytrans.com | G88: 081 58 21 91 | H88: verhuis & meubelopslag
A89: Ultra Lift | B89: Transport & logistiek | C89: Verhuisfirma | D89: ultra-lift.be | E89: Brussel | F89: info@ultra-lift.be | G89: 0488 61 33 60 | H89: >14 jaar; verhuis & ladderlift
A90: Uyttendaele Europese Verhuizingen | B90: Transport & logistiek | C90: Verhuisfirma | D90: verhuisfirma-uyttendaele.be | E90: Aarschot | F90: info@verhuisfirma-uyttendaele.be | G90: +32 16 62 04 71 | H90: >45 jaar
A91: VDS Van Der Smissen Verhuizingen | B91: Transport & logistiek | C91: Verhuisfirma | D91: verhuizingenvandersmissen.be | E91: Relegem (Asse) | G91: +32 498 10 07 00 | H91: geen e-mail gevonden
A92: Verhuizingen Bonte | B92: Transport & logistiek | C92: Verhuisfirma | D92: verhuizingenbonte.be | E92: Brugge | F92: info@verhuizingenbonte.be | G92: 050 33 66 00 | H92: 5 vestigingen; >90 jaar
A93: Verhuizingen Deceuninck | B93: Transport & logistiek | C93: Verhuisfirma | E93: Roeselare | G93: 0492 88 67 53 | H93: geen e-mail gevonden
A94: Verhuizingen Hoeks | B94: Transport & logistiek | C94: Verhuisfirma | D94: hoeks.be | E94: Lommel / Hasselt | F94: info@hoeks.be | G94: 011 66 00 50 | H94: BKV erkend verhuizer
A95: Verhuizingen Jespers | B95: Transport & logistiek | C95: Verhuisfirma | D95: verhuizingenjespers.com | E95: Leuven | G95: 0499 42 23 80 | H95: geen e-mail gevonden
A96: Verhuizingen Schollaert | B96: Transport & logistiek | C96: Verhuisfirma | E96: Gent | G96: 09 225 10 85 | H96: geen e-mail gevonden
A97: Verhuizingen Schreurs | B97: Transport & logistiek | C97: Verhuisfirma | D97: verhuizingenschreurs.be | E97: Hasselt | F97: info@verhuizingenschreurs.be | H97: geen telefoon in zoekresultaat
A98: Verhuizingen Troch | B98: Transport & logistiek | C98: Verhuisfirma | D98: verhuizingentroch.be | E98: Genk | F98: info@verhuizingentroch.be | G98: +32 473 69 69 92 | H98: sinds 2017
A99: Vervaet Verhuis | B99: Transport & logistiek | C99: Verhuisfirma | D99: vervaetverhuis.be | E99: Aalter | F99: info@vervaetverhuis.be | G99: +32 9 331 57 80
A100: Victor et Fils | B100: Transport & logistiek | C100: Verhuisfirma | D100: victoretfils.be | E100: Schaarbeek (Brussel) | F100: info@victoretfils.be | G100: +32 2 215 36 59 | H100: 70 jaar ervaring
...

Sheet Bouw
A1: Bedrijfsnaam | B1: Sector | C1: Subcategorie | D1: Website | E1: Plaats | F1: E-mailadres | G1: Telefoon | H1: Opmerking (omvang / verificatie)
A2: AK Building Woningbouw & Renovatie | B2: Bouw | C2: Algemene aannemer | D2: akbuilding.be | E2: Zonhoven | F2: info@akbuilding.be | G2: +32 483 51 24 67 | H2: ruwbouw & totaalrenovatie
A3: ALFA•VAF | B3: Bouw | C3: Algemene aannemer | D3: alfavaf.be | E3: Eksaarde (Lokeren) | F3: info@alfavaf.be | G3: +32 468 29 00 85 | H3: omvang niet geverifieerd
A4: Algemene Bouwonderneming Debal Erik | B4: Bouw | C4: Algemene aannemer | D4: bouwondernemingdebalerik.be | E4: Roeselare | F4: info@debalerik.be | G4: 051 20 83 41 | H4: >50 jaar actief
A5: Algemene Bouwonderneming Toon Willems | B5: Bouw | C5: Algemene aannemer | D5: abtoonwillems.be | E5: Geel | F5: info@abtoonwillems.be | G5: 0498 57 54 45 | H5: omvang niet geverifieerd
A6: Algemene Bouwwerken Steven Kegels | B6: Bouw | C6: Algemene aannemer | D6: abstevenkegelsbv.be | E6: Sint-Niklaas | G6: 0478 36 00 39 | H6: e-mail afgeschermd op website
A7: All-Bouw | B7: Bouw | C7: Algemene aannemer | D7: allbouw.com | E7: Roeselare | F7: info@allbouw.com | G7: +32 51 25 30 25 | H7: nieuwbouw, renovatie & restauratie
A8: AMD Bouw | B8: Bouw | C8: Algemene aannemer | D8: amdbouw.be | E8: Sint-Laureins | G8: 0467 74 81 62 | H8: e-mail afgeschermd; bouw, elektriciteit, sanitair
A9: Arco Villa | B9: Bouw | C9: Algemene aannemer | D9: arcovilla.be | E9: Sprimont | F9: fm@arcovilla.be | G9: +32 4 372 15 92 | H9: >25 jaar; adres lijkt persoonsgebonden
A10: ARP Bouw & Interieur | B10: Bouw | C10: Algemene aannemer | D10: arp-bouw.be | E10: Hasselt | F10: info@arp-bouw.be | G10: +32 472 43 82 79 | H10: sinds 2010
A11: Audenaert Eddy & Zonen | B11: Bouw | C11: Algemene aannemer | D11: audenaertconstruct.be | E11: Sint-Niklaas | G11: +32 3 776 57 01 | H11: geen publiek e-mailadres gevonden
A12: Bouwbedrijf Gevaco | B12: Bouw | C12: Algemene aannemer | D12: bouwbedrijfgevaco.be | E12: Mol | F12: info@bouwbedrijfgevaco.be | G12: 014 71 64 54
A13: Bouwonderneming De Clippel | B13: Bouw | C13: Algemene aannemer | D13: declippel.be | E13: Herzele | F13: info@declippel.be | G13: 053 62 24 55 | H13: erkend aannemer klasse 5 sinds 1945; mogelijk >30 werknemers
A14: Bouwonderneming Kris Van Ostaeyen | B14: Bouw | C14: Algemene aannemer | D14: krisvanostaeyen.be | E14: Zandhoven | F14: info@krisvanostaeyen.be | G14: 0477 45 76 88 | H14: ruwbouw & renovatie
A15: Bouwwerken Goderis | B15: Bouw | C15: Algemene aannemer | D15: bouwwerkengoderis.be | E15: Tielt | G15: 0479 13 01 10 | H15: geen e-mail gevonden
A16: C/B Bouw | B16: Bouw | C16: Algemene aannemer | E16: West-Vlaanderen | G16: 050 54 66 52 | H16: geen e-mail gevonden
A17: DC Technic | B17: Bouw | C17: Algemene aannemer | D17: dcbouw.com | E17: Leuven | F17: info@dcbouw.com | H17: aannemer & schrijnwerkerij; geen telefoon in zoekresultaat
A18: Deruyck Bouwonderneming | B18: Bouw | C18: Algemene aannemer | D18: deruyckbouw.be | E18: Roeselare | F18: info@deruyckbouw.be | G18: 051 20 26 03 | H18: familiebedrijf; omvang niet geverifieerd
A19: Heres Bouwprojecten | B19: Bouw | C19: Algemene aannemer | D19: heres-bouw.be | E19: Oud-Turnhout | F19: info@heres-bouw.be | G19: +32 473 96 11 09 | H19: omvang niet geverifieerd
A20: Houtbouw Kempen | B20: Bouw | C20: Algemene aannemer | D20: houtbouwkempen.be | E20: Mol | F20: info@houtbouwkempen.be | G20: +32 473 64 64 19 | H20: houtskeletbouw; omvang niet geverifieerd
A21: Industriebouw Vaneenoo | B21: Bouw | C21: Algemene aannemer | D21: vaneenoo.be | E21: Wingene | G21: +32 51 65 61 78 | H21: geen algemeen e-mailadres gevonden
A22: K&W Construction | B22: Bouw | C22: Algemene aannemer | D22: kwconstruction.be | E22: Wortegem-Petegem | F22: info@kwconstruction.be | G22: +32 55 45 79 73 | H22: omvang niet geverifieerd
A23: KBX Bouwonderneming | B23: Bouw | C23: Algemene aannemer | D23: kbxbvba.be | E23: Herentals | F23: info@kbxbvba.be | G23: +32 471 60 16 22 | H23: omvang niet geverifieerd
A24: LeF! | B24: Bouw | C24: Algemene aannemer | D24: bouwenmetlef.be | E24: Mol | F24: info@bouwenmetlef.be | G24: 0468 48 64 82 | H24: nieuwbouw en renovatie; omvang niet geverifieerd
A25: Ooms Woonrealisaties | B25: Bouw | C25: Algemene aannemer | D25: ooms.be | E25: Rijkevorsel | F25: info@ooms.be | G25: +32 3 309 09 09 | H25: totaalaannemer; mogelijk >30 werknemers
A26: Standing Construct | B26: Bouw | C26: Algemene aannemer | D26: standingconstruct.be | E26: Geel | F26: info@standingconstruct.be | G26: +32 14 58 27 20 | H26: 4e generatie, eigen vaklui; omvang niet geverifieerd
A27: Stonehouse | B27: Bouw | C27: Algemene aannemer | D27: stonehouse.be | E27: Boutersem | F27: info@stonehouse.be | G27: +32 475 47 46 96
A28: Van der Steen Algemene Bouwonderneming | B28: Bouw | C28: Algemene aannemer | D28: van-der-steen.be | E28: Leuven | F28: info@van-der-steen.be | G28: 016 48 94 17
A29: Woestenborghs Bouwbedrijf | B29: Bouw | C29: Algemene aannemer | D29: woestenborghs-bouwbedrijf.be | E29: Merksplas | G29: +32 14 63 38 04 | H29: geen algemeen e-mailadres gevonden
A30: Woningbouw Vens | B30: Bouw | C30: Algemene aannemer | D30: vens.be | E30: Zwevezele (Wingene) | F30: info@vens.be | G30: 051 61 12 19 | H30: sleutel-op-de-deur
A31: XL Construction | B31: Bouw | C31: Algemene aannemer | D31: xlconstruction.be | E31: Pousset (Remicourt) | F31: info@xlconstruction.be | G31: 04 332 26 10 | H31: sleutel-op-de-deur, Wallonië
A32: Algemene Elektriciteitswerken Jordy Danckaert | B32: Bouw | C32: Installatiebedrijf (elektriciteit) | D32: jordydanckaert.be | E32: Grembergen (Dendermonde) | F32: info@jordydanckaert.be | G32: 0476 07 52 98 | H32: omvang niet geverifieerd
A33: Brackx Elektriciteitswerken | B33: Bouw | C33: Installatiebedrijf (elektriciteit) | D33: e-brackx.be | E33: Oostende | F33: info@e-brackx.be | G33: 0497 29 15 80 | H33: omvang niet geverifieerd
A34: CL Electric | B34: Bouw | C34: Installatiebedrijf (elektriciteit) | D34: clelectric.be | E34: Oostende | G34: +32 477 89 41 40 | H34: geen publiek e-mailadres gevonden
A35: De Hondt Elektriciteitswerken | B35: Bouw | C35: Installatiebedrijf (elektriciteit) | D35: dehondtelektriciteitswerken.be | E35: Diepenbeek | F35: info@dehondtelektriciteitswerken.be | G35: 0468 15 01 22 | H35: omvang niet geverifieerd
A36: Denis Wilrijkse Electrowerken | B36: Bouw | C36: Installatiebedrijf (elektriciteit) | D36: deniswilrijkelectro.be | E36: Wilrijk (Antwerpen) | F36: info@deniswilrijkelectro.be | G36: 0476 02 97 02 | H36: sinds 1960; omvang niet geverifieerd
A37: Electro Corbeels | B37: Bouw | C37: Installatiebedrijf (elektriciteit) | D37: corbeels.be | E37: Holsbeek | F37: info@corbeels.be | G37: +32 16 23 87 11 | H37: residentieel & industrieel
A38: Elektriciteitswerken Vanhaverbeke | B38: Bouw | C38: Installatiebedrijf (elektriciteit) | D38: elektriciteitswerkenvanhaverbeke.be | E38: Izegem | F38: info@elektriciteitswerkenvanhaverbeke.be | G38: +32 472 27 00 90 | H38: omvang niet geverifieerd
A39: Elektro Jos | B39: Bouw | C39: Installatiebedrijf (elektriciteit) | D39: elektrojos.be | E39: Izegem | F39: info@elektrojos.be | G39: +32 476 85 56 66 | H39: omvang niet geverifieerd
A40: ENW Elektriciteitswerken | B40: Bouw | C40: Installatiebedrijf (elektriciteit) | D40: enwelektriciteitswerken.be | E40: Aarschot (Rillaar) | G40: +32 16 50 31 24 | H40: geen e-mail gevonden
A41: Fiabelec | B41: Bouw | C41: Installatiebedrijf (elektriciteit) | E41: Frameries | G41: 065 95 60 71 | H41: website niet vermeld; geen e-mail gevonden
A42: JNP | B42: Bouw | C42: Installatiebedrijf (elektriciteit) | D42: jnpbvba.be | E42: Houthalen-Oost | F42: info@jnpbvba.be | G42: 0475 45 30 03 | H42: klein (elektricien + interieurarchitect); onder criterium
A43: JSE Elektriciteitswerken | B43: Bouw | C43: Installatiebedrijf (elektriciteit) | D43: jse-bv.be | E43: Bekkevoort | F43: info@jse-bv.be | G43: 016 20 33 09 | H43: omvang niet geverifieerd
A44: Lee Elektro | B44: Bouw | C44: Installatiebedrijf (elektriciteit) | D44: lee-elektro.be | E44: Aalst | F44: info@lee-elektro.be | G44: 0498 52 19 00 | H44: omvang niet geverifieerd
A45: Nicolas Talpe Elektriciteitswerken | B45: Bouw | C45: Installatiebedrijf (elektriciteit) | D45: nicolastalpe-elektriciteitswerken.be | E45: Zonnebeke (regio Ieper) | F45: info@nicolastalpe-elektriciteitswerken.be | G45: 0497 78 87 27 | H45: omvang niet geverifieerd; mogelijk klein
A46: VP Elektriciteit | B46: Bouw | C46: Installatiebedrijf (elektriciteit) | D46: vpelektriciteit.be | E46: Heist-op-den-Berg | F46: info@vpelektriciteit.be | G46: 0474 23 33 75 | H46: familiebedrijf sinds 1965; omvang niet geverifieerd
A47: Andy Raes | B47: Bouw | C47: Installatiebedrijf (sanitair/verwarming) | D47: centraleverwarmingraesandy.be | E47: Denderhoutem (Haaltert) | F47: andy.raes01@gmail.com | G47: +32 474 69 87 21 | H47: persoonlijk adres; omvang niet geverifieerd
A48: Arnold CV | B48: Bouw | C48: Installatiebedrijf (sanitair/verwarming) | D48: arnoldcv.be | E48: West- en Oost-Vlaanderen (meerdere locaties) | G48: 0475 34 18 09 | H48: mogelijk >30 werknemers; geen publiek e-mailadres gevonden
A49: BE Sanitair & Verwarming | B49: Bouw | C49: Installatiebedrijf (sanitair/verwarming) | D49: be-sanitair.be | E49: Herentals | F49: info@be-sanitair.be | G49: 014 55 35 82 | H49: familiebedrijf sinds 1997
A50: Bondec | B50: Bouw | C50: Installatiebedrijf (sanitair/verwarming) | D50: bondec.be | E50: Wommelgem | F50: verkoop@bondec.be | G50: +32 3 239 31 47 | H50: HVAC; afdelingsadressen (verkoop@, herstellingen@)
A51: Climatherm | B51: Bouw | C51: Installatiebedrijf (sanitair/verwarming) | D51: climatherm.be | E51: Brugge | F51: info@climatherm.be | G51: 050 32 30 91 | H51: verwarming, ventilatie, airco; omvang niet geverifieerd
A52: CT-O | B52: Bouw | C52: Installatiebedrijf (sanitair/verwarming) | D52: ct-o.be | E52: Oostkamp | H52: fusie CentroTherm/Obers/Caestecker; mogelijk >30 werknemers; contact via website
A53: CV-San De Coninck | B53: Bouw | C53: Installatiebedrijf (sanitair/verwarming) | D53: cvdeconinck.be | E53: Sint-Katelijne-Waver | F53: sanitair.deconinck@telenet.be | G53: 0473 76 11 95
A54: Daniels Verwarming en Sanitair | B54: Bouw | C54: Installatiebedrijf (sanitair/verwarming) | E54: Herk-de-Stad | F54: francis.daniels@scarlet.be | G54: 0475 85 77 62 | H54: persoonlijk adres
A55: Develtere | B55: Bouw | C55: Installatiebedrijf (sanitair/verwarming) | D55: develtere.be | E55: Roeselare | G55: +32 51 24 24 25 | H55: geen e-mail gevonden
A56: Easy San | B56: Bouw | C56: Installatiebedrijf (sanitair/verwarming) | D56: easysan.be | E56: Diepenbeek | F56: info@easysan.be | G56: 0466 04 11 20 | H56: >15 jaar
A57: Emiel | B57: Bouw | C57: Installatiebedrijf (sanitair/verwarming) | D57: emielbvba.be | E57: Merksem (Antwerpen) | G57: 0474 61 89 89 | H57: geen e-mail gevonden
A58: GB Technics | B58: Bouw | C58: Installatiebedrijf (sanitair/verwarming) | D58: gbtechnics.be | E58: Ninove | F58: info@gbtechnics.be | G58: 0496 87 57 48 | H58: CV, sanitair, elektriciteit
A59: Geldof Technics | B59: Bouw | C59: Installatiebedrijf (sanitair/verwarming) | D59: geldof-technics.be | E59: Beernem | G59: +32 50 69 71 09 | H59: geen publiek e-mailadres gevonden
A60: Guilliams Jo | B60: Bouw | C60: Installatiebedrijf (sanitair/verwarming) | D60: joguilliams.be | E60: Mielen-boven-Aalst (Gingelom) | F60: info@joguilliams.be | G60: 011 48 60 41 | H60: verwarming, ventilatie & elektriciteit
A61: Jeanfils et Fils | B61: Bouw | C61: Installatiebedrijf (sanitair/verwarming) | D61: jeanfils.be | E61: Verlaine | G61: 04 259 50 54 | H61: geen algemeen e-mailadres gevonden; 4 generaties
A62: Kevin Brackx Technics | B62: Bouw | C62: Installatiebedrijf (sanitair/verwarming) | D62: brackxkevin-technics.be | E62: West-Vlaanderen | G62: 050 21 56 52 | H62: omvang niet geverifieerd; mogelijk klein
A63: LC Chauffage | B63: Bouw | C63: Installatiebedrijf (sanitair/verwarming) | D63: lc-chauffage.be | E63: Brabant wallon / Namur / Liège | F63: info@lc-chauffage.be | G63: +32 494 33 62 49 | H63: verwarming, sanitair & daken
A64: Lemco | B64: Bouw | C64: Installatiebedrijf (sanitair/verwarming) | D64: lemco-nv.be | E64: Berchem (Antwerpen) | G64: 03 230 66 89 | H64: CV, sanitair, HVAC & elektriciteit; geen e-mail gevonden
A65: Lemmens Verwarming - Sanitair | B65: Bouw | C65: Installatiebedrijf (sanitair/verwarming) | E65: Lommel | F65: lemmensverwarming-sanitair@outlook.com | G65: 0474 44 47 48 | H65: opgericht 2017; omvang niet geverifieerd
A66: Muermans | B66: Bouw | C66: Installatiebedrijf (sanitair/verwarming) | D66: muermansbvba.be | E66: Hasselt | F66: muermans@telenet.be | G66: 011 22 86 56 | H66: ±50 jaar actief
A67: Sanecal | B67: Bouw | C67: Installatiebedrijf (sanitair/verwarming) | D67: sanecal.be | E67: Oostende | F67: info@sanecal.be | G67: 059 55 16 66 | H67: >50 jaar actief
A68: Sanitair & CV Persy (SCP) | B68: Bouw | C68: Installatiebedrijf (sanitair/verwarming) | D68: kevinpersy.be | E68: Mechelen | F68: info@scp-bvba.be | G68: 0496 35 02 74 | H68: omvang niet geverifieerd
A69: Sanitair Blondeel | B69: Bouw | C69: Installatiebedrijf (sanitair/verwarming) | D69: sanitairblondeel.be | E69: Kortrijk (Marke) | G69: +32 56 22 20 12 | H69: 3 generaties; geen publiek e-mailadres gevonden
A70: Saniver-Gent | B70: Bouw | C70: Installatiebedrijf (sanitair/verwarming) | D70: saniver.be | E70: Gent (Oostakker) | G70: 0475 47 95 07 | H70: familiebedrijf, 30+ jaar; geen publiek e-mailadres gevonden
A71: Technibo | B71: Bouw | C71: Installatiebedrijf (sanitair/verwarming) | D71: technibo.be | E71: Leuven | F71: info@technibo.be | G71: +32 475 28 66 45 | H71: ook elektriciteit; omvang niet geverifieerd
A72: Van Driessche Johan | B72: Bouw | C72: Installatiebedrijf (sanitair/verwarming) | D72: vandriessche.be | E72: Denderleeuw | F72: info@vandriessche.be | G72: 0478 47 03 44 | H72: omvang niet geverifieerd
A73: Van Immerseel | B73: Bouw | C73: Installatiebedrijf (sanitair/verwarming) | D73: vanimmerseel-bvba.be | E73: Mechelen | F73: info@vanimmerseel-bvba.be | G73: +32 15 55 62 41 | H73: CV, sanitair, elektriciteit, ventilatie; omvang niet geverifieerd
A74: Van Vlimmeren | B74: Bouw | C74: Installatiebedrijf (sanitair/verwarming) | D74: vanvlimmerenbvba.be | E74: Deurne (Antwerpen) | G74: 03 321 11 94 | H74: geen e-mail bekend; ±75 jaar actief
A75: Vanbetsbrugge | B75: Bouw | C75: Installatiebedrijf (sanitair/verwarming) | D75: vanbetsbrugge-nv.be | E75: West-Vlaanderen (regio Kortrijk) | F75: info@vanbetsbrugge-nv.be | G75: 056 60 88 81 | H75: HVAC, sanitair, centrale verwarming
A76: Vanderstraeten Sanitair-Verwarming | B76: Bouw | C76: Installatiebedrijf (sanitair/verwarming) | D76: vanderstraeten-sanitair-verwarming.be | E76: — | F76: rafaelvanderstraeten@outlook.com | G76: 0493 33 71 34 | H76: persoonlijk adres; omvang niet geverifieerd
A77: Vanhollebeke | B77: Bouw | C77: Installatiebedrijf (sanitair/verwarming) | D77: vanhollebeke-verwarming.be | E77: Kortrijk | F77: info@vanhollebeke-verwarming.be | G77: 056 22 23 39 | H77: omvang niet geverifieerd
A78: Vanneste | B78: Bouw | C78: Installatiebedrijf (sanitair/verwarming) | D78: vanneste-bvba.be | E78: Brugge | F78: info@vannestebv.be | G78: 050 31 31 41 | H78: HVAC-specialist sinds 1994; omvang niet geverifieerd
A79: VDV | B79: Bouw | C79: Installatiebedrijf (sanitair/verwarming) | D79: vdvbvba.be | E79: Duffel | F79: vdvbvba@telenet.be | G79: 0496 78 39 32 | H79: ook elektriciteit; omvang niet geverifieerd
A80: Verrezen HVAC | B80: Bouw | C80: Installatiebedrijf (sanitair/verwarming) | D80: verrezenhvac.be | E80: Kapelle-op-den-Bos | F80: info@verrezenhvac.be | G80: +32 483 38 23 31 | H80: omvang niet geverifieerd
A81: Vijverman Verwarming | B81: Bouw | C81: Installatiebedrijf (sanitair/verwarming) | D81: vijvermanverwarming.be | E81: Denderleeuw | F81: info@vijvermanverwarming.be | G81: 0478 39 07 68 | H81: omvang niet geverifieerd
A82: Wachtelaer | B82: Bouw | C82: Installatiebedrijf (sanitair/verwarming) | D82: wachtelaerbv.be | E82: Ninove | F82: info@geert-wachtelaer.be | G82: 054 33 25 19 | H82: ook elektriciteit en zonnepanelen; omvang niet geverifieerd
A83: Établissements Vrancken | B83: Bouw | C83: Installatiebedrijf (sanitair/verwarming) | D83: chauffage-vrancken.be | E83: Liège (Grivegnée) | F83: info@chauffage-vrancken.be | G83: 04 343 44 37 | H83: familiebedrijf >115 jaar
A84: 2 Renew | B84: Bouw | C84: Renovatiebedrijf | D84: 2renew.be | E84: Antwerpen | F84: info@2renew.be | G84: 0496 82 82 84 | H84: 18 jaar ervaring
A85: A-Renovatie | B85: Bouw | C85: Renovatiebedrijf | D85: a-renovatie.be | E85: Antwerpen / Vlaams-Brabant | F85: contact@a-renovatie.be | G85: 014 58 10 66 | H85: nieuwbouw & renovatie
A86: Abso | B86: Bouw | C86: Renovatiebedrijf | D86: abso.be | E86: Evergem | F86: info@abso.be | G86: 09 226 66 60 | H86: afbraak, grondwerken, renovatie; omvang niet geverifieerd
... A88: Alrebo | B88: Bouw | C88: Renovatiebedrijf | D88: algemenerenovatiebouw.be | E88: Oostakker (Gent) | F88: info@alrebo.be | G88: 0478 30 19 87 | H88: omvang niet geverifieerd
A89: ATOM Construction | B89: Bouw | C89: Renovatiebedrijf | D89: atomconstruction.be | E89: Liège (+ Namur, Brabant) | G89: +32 2 274 48 00 | H89: >10 jaar; e-mail afgeschermd
A90: Bear Renovations | B90: Bouw | C90: Renovatiebedrijf | D90: bear-renovations.com | E90: Mechelen / Antwerpen | G90: +32 468 25 55 52 | H90: geen e-mail gevonden
A91: BK Concept | B91: Bouw | C91: Renovatiebedrijf | D91: bkconcept.be | E91: Maasmechelen / Limburg | F91: info@bkconcept.be | G91: 089 70 00 04 | H91: totaalrenovatie; omvang niet geverifieerd
A92: Bruggemans Construct | B92: Bouw | C92: Renovatiebedrijf | D92: bruggemans.be | E92: Tielt-Winge | F92: info@bruggemans.be | G92: +32 16 82 07 99 | H92: nieuwbouw & renovatie
A93: DAG Bouw | B93: Bouw | C93: Renovatiebedrijf | D93: dagbouw.be | E93: Herk-de-Stad | F93: info@dagbouw.be | G93: 0489 94 49 72 | H93: omvang niet geverifieerd
A94: Dams Bouwwerken | B94: Bouw | C94: Renovatiebedrijf | D94: damsbouwwerken.be | E94: Geel | F94: dams.bouwwerken@skynet.be | G94: 014 22 45 21 | H94: omvang niet geverifieerd
A95: Gebroeders Luyckx Algemene Bouw en Dakwerken | B95: Bouw | C95: Renovatiebedrijf | D95: gebroedersluyckx.be | E95: Hever (Boortmeerbeek) | F95: gebroeders.luyckx@telenet.be | G95: 015 52 06 03 | H95: renovatie & dakwerken
A96: Gentbouw | B96: Bouw | C96: Renovatiebedrijf | D96: gentbouw.be | E96: Gent | G96: 0475 48 94 71 | H96: geen e-mail gevonden
A97: Rinovato | B97: Bouw | C97: Renovatiebedrijf | D97: rinovato.be | E97: Gent | G97: +32 468 21 35 07 | H97: deel van Facibel; geen e-mail gevonden
A98: Van Damme Construction | B98: Bouw | C98: Renovatiebedrijf | D98: vandammeconstruction.be | E98: Gent (Gentbrugge) | F98: info@vandammeconstruction.be | G98: 09 391 64 01 | H98: omvang niet geverifieerd
A99: Vandeweyer Renov | B99: Bouw | C99: Renovatiebedrijf | D99: vandeweyerrenov-hasselt.be | E99: Hasselt | F99: dolf.vandeweyer@skynet.be | G99: 0473 93 47 54 | H99: persoonlijk adres; omvang niet geverifieerd
A100: VDN Construct | B100: Bouw | C100: Renovatiebedrijf | D100: vdnconstruct.be | E100: Zandhoven | G100: 0479 96 84 27 | H100: geen e-mail gevonden
A101: VDS Works | B101: Bouw | C101: Renovatiebedrijf | D101: vdsworks.be | E101: Izegem | G101: 0491 74 60 83 | H101: renovatie en elektriciteit; e-mail afgeschermd op website

Sheet Vastgoed
A1: Bedrijfsnaam | B1: Sector | C1: Subcategorie | D1: Website | E1: Plaats | F1: E-mailadres | G1: Telefoon | H1: Opmerking (omvang / verificatie)
A2: Abricasa | B2: Vastgoed | C2: Makelaarskantoor | D2: abricasa.be | E2: Antwerpen | F2: info@abricasa.be | G2: 03 259 04 04 | H2: BIV 506656
A3: AC Vastgoed | B3: Vastgoed | C3: Makelaarskantoor | D3: acvastgoed.be | E3: Sint-Niklaas | F3: info@acvastgoed.be | G3: 03 777 93 93
A4: AD-IMMO | B4: Vastgoed | C4: Makelaarskantoor | D4: ad-immo.be | E4: Namur | F4: info@ad-immo.be | G4: 081 74 73 75
A5: AG Immobilière | B5: Vastgoed | C5: Makelaarskantoor | D5: agimmobiliere.be | E5: Rocourt (Liège) | F5: info@agimmobiliere.be | G5: 04 233 55 55
A6: Agence Rosseel | B6: Vastgoed | C6: Makelaarskantoor | D6: rosseel.be | E6: Gent | G6: 09 220 50 00 | H6: alleen persoonlijke e-mailadressen; verkoop, verhuur, rentmeesterschap
A7: Axel Lenaerts Makelaars | B7: Vastgoed | C7: Makelaarskantoor | D7: axellenaerts.be | E7: Gent / Oudenaarde | F7: info@axellenaerts.be | G7: 09 245 24 24 | H7: meerdere kantoren
A8: BM Vastgoed | B8: Vastgoed | C8: Makelaarskantoor | D8: bmvastgoed.be | E8: Mechelen / Leuven | F8: info@bmvastgoed.be | G8: 015 79 15 99 | H8: 2 kantoren
A9: Bricx Vastgoed (Kortrijk) | B9: Vastgoed | C9: Makelaarskantoor | D9: bricx.be | E9: Kortrijk | F9: kortrijk@bricx.be | G9: 056 36 03 00 | H9: meerdere kantoren
A10: Claves Vastgoed | B10: Vastgoed | C10: Makelaarskantoor | D10: claves.be | E10: Sint-Niklaas | F10: vastgoed@claves.be | G10: +32 3 502 98 74
A11: Copandi | B11: Vastgoed | C11: Makelaarskantoor | D11: copandi.be | E11: Mechelen / Lier | F11: info@copandi.be | G11: +32 15 79 46 44 | H11: meerdere kantoren
A12: Cornelis Goeman | B12: Vastgoed | C12: Makelaarskantoor | D12: cornelis-goeman.be | E12: Merelbeke / Lede (+ 6 kantoren) | F12: immo@cornelis-partners.be | G12: +32 9 232 21 50 | H12: 8 kantoren in Oost-Vlaanderen
A13: De Boer & Partners (Turnhout) | B13: Vastgoed | C13: Makelaarskantoor | D13: deboerenpartners.be | E13: Turnhout | F13: karen.woestenborghs@deboerenpartners.be | G13: +32 14 22 42 00 | H13: persoonlijk adres; meerdere kantoren
A14: De Makelaardij | B14: Vastgoed | C14: Makelaarskantoor | D14: demakelaardij.be | E14: Mechelen | F14: info@demakelaardij.be | G14: 015 20 20 82
A15: De Vastgoedkoning | B15: Vastgoed | C15: Makelaarskantoor | D15: devastgoedkoning.be | E15: Aarschot | F15: info@devastgoedkoning.be | G15: 016 78 95 55
A16: Dicasa | B16: Vastgoed | C16: Makelaarskantoor | D16: dicasa.be | E16: Roeselare (Beveren) | F16: info@dicasa.be | G16: 051 20 14 00 | H16: ook syndicus
A17: Diksimmo | B17: Vastgoed | C17: Makelaarskantoor | D17: diksimmo.be | E17: Ieper / Diksmuide | F17: ieper@diksimmo.be | G17: +32 57 79 75 00
A18: Dor & Bleus | B18: Vastgoed | C18: Makelaarskantoor | D18: immodorbleus.be | E18: Liège | F18: dor@dorbleus.be | G18: +32 4 223 21 88 | H18: sinds 2012
A19: Elissa Agence Immobilière | B19: Vastgoed | C19: Makelaarskantoor | D19: immoelissa.be | E19: Liège | F19: info@immoelissa.be | G19: 04 221 02 21
A20: ERA Domus | B20: Vastgoed | C20: Makelaarskantoor | D20: era.be | E20: Ieper (+ Veurne, Diksmuide, Poperinge, Roeselare) | F20: domus.ieper@era.be | G20: +32 57 21 36 96 | H20: meerdere kantoren
A21: ERA Wonen Sint-Niklaas | B21: Vastgoed | C21: Makelaarskantoor | D21: era.be | E21: Sint-Niklaas | F21: hello@era.be | G21: +32 3 269 37 69 | H21: ERA-netwerk; algemeen adres van ERA
A22: Heylen Vastgoed Mechelen | B22: Vastgoed | C22: Makelaarskantoor | D22: heylenvastgoed.be | E22: Mechelen | F22: info@heylenexclusief.be | G22: 0800 292 23 | H22: groot netwerk; adres van Heylen Exclusief
A23: Huiskantoor | B23: Vastgoed | C23: Makelaarskantoor | D23: huiskantoor.be | E23: Lommel / Pelt / Bree | F23: info@huiskantoor.be | G23: 011 91 90 50 | H23: 3 kantoren
A24: Huys Noord Immobiliën | B24: Vastgoed | C24: Makelaarskantoor | D24: huysnoord.be | E24: Brugge | F24: contact@huysnoord.be | G24: 050 70 06 00
A25: Huyzen Sint-Niklaas | B25: Vastgoed | C25: Makelaarskantoor | D25: huyzen.be | E25: Belsele (Sint-Niklaas) | G25: 03 775 03 30 | H25: deel van Huyzen Vastgoedgroep; e-mail afgeschermd
A26: i-Moov | B26: Vastgoed | C26: Makelaarskantoor | D26: i-moov.be | E26: Gent | F26: info@i-moov.be | G26: +32 9 225 50 50 | H26: aantal panden niet geverifieerd
A27: Immo Consulting Wallays | B27: Vastgoed | C27: Makelaarskantoor | D27: immowallays.be | E27: Roeselare | G27: 051 24 88 00 | H27: familiekantoor >50 jaar; geen e-mail gevonden
A28: Immo Da Vinci | B28: Vastgoed | C28: Makelaarskantoor | D28: immodavinci.be | E28: Gent | F28: info@immodavinci.be | G28: 09 273 55 55
A29: Immo Francois | B29: Vastgoed | C29: Makelaarskantoor | D29: immofrancois.be | E29: Loppem (Zedelgem) – 24 kantoren | F29: dries@immofrancois.be | G29: 050 32 34 34 | H29: netwerk van 24 kantoren; persoonlijk adres
A30: Immo GVE | B30: Vastgoed | C30: Makelaarskantoor | D30: immogve.be | E30: Leuven (+ Tienen, Aarschot, Bertem) | F30: info@immogve.be | G30: 016 56 56 14 | H30: 4 kantoren
A31: Immo Jo | B31: Vastgoed | C31: Makelaarskantoor | D31: jo.immo | E31: Oostende | F31: jo@jo.immo | G31: +32 59 30 08 00
A32: Immo Minnaert & C° | B32: Vastgoed | C32: Makelaarskantoor | D32: immominnaert.be | E32: Hasselt | F32: patrick@immominnaert.be | G32: +32 11 21 44 53 | H32: persoonlijk adres
A33: Immo Sleutel | B33: Vastgoed | C33: Makelaarskantoor | D33: immosleutel.be | E33: Brugge | F33: info@immosleutel.be | G33: +32 50 70 70 70
A34: Immo Vastgoed Turnhout | B34: Vastgoed | C34: Makelaarskantoor | D34: vastgoedturnhout.be | E34: Turnhout | F34: info@vastgoedturnhout.be | G34: 014 42 33 85 | H34: sinds 1992
A35: imo Vastgoed Mechelen | B35: Vastgoed | C35: Makelaarskantoor | D35: imovastgoed.be | E35: Mechelen | G35: +32 479 88 27 55 | H35: deel van imo Vastgoed Groep; e-mail niet in zoekresultaat
A36: INFORIM | B36: Vastgoed | C36: Makelaarskantoor | D36: inforim.be | E36: Liège | F36: info@inforim.be | H36: geen telefoon in zoekresultaat
A37: L'Immobilière L.A. | B37: Vastgoed | C37: Makelaarskantoor | D37: agence-immobiliere-namur.be | E37: Namur | F37: contact@agence-immobiliere-namur.be | H37: geen telefoon in zoekresultaat
A38: La Signature | B38: Vastgoed | C38: Makelaarskantoor | D38: lasignature.be | E38: Hognoul / Embourg (Liège) | F38: info@lasignature.be | G38: 04 223 30 30 | H38: 2 kantoren
A39: Loontjens & Lagast Vastgoed | B39: Vastgoed | C39: Makelaarskantoor | D39: llvastgoed.be | E39: Brugge | F39: info@llvastgoed.be | G39: +32 50 20 02 00
A40: Makelaarshuys | B40: Vastgoed | C40: Makelaarskantoor | D40: makelaarshuys.be | E40: Gent | F40: alain@makelaarshuys.be | G40: 09 277 10 27 | H40: persoonlijk adres; aantal panden niet geverifieerd
A41: Makelaarskantoor De Meester | B41: Vastgoed | C41: Makelaarskantoor | D41: demeester.eu | E41: Antwerpen | F41: info@demeester.eu | G41: 03 227 06 36 | H41: sinds 1994
A42: MCA-Vastgoed | B42: Vastgoed | C42: Makelaarskantoor | D42: mca-vastgoed.be | E42: Hasselt | F42: info@mca-vastgoed.be | G42: 0485 34 56 71
A43: Momentum Vastgoed | B43: Vastgoed | C43: Makelaarskantoor | D43: momentumvastgoed.be | E43: Hasselt / Genk | F43: info@momentumvastgoed.be | G43: +32 11 96 51 76
A44: Oh My George | B44: Vastgoed | C44: Makelaarskantoor | D44: ohmygeorge.be | E44: Antwerpen | F44: karen@ohmygeorge.be | G44: +32 474 25 99 25 | H44: persoonlijk adres
A45: Partners in Vastgoed | B45: Vastgoed | C45: Makelaarskantoor | D45: partnersinvastgoed.be | E45: Ieper | F45: frederic@partnersinvastgoed.be | G45: +32 57 21 93 36 | H45: persoonlijk adres
A46: Realisten Makelaars | B46: Vastgoed | C46: Makelaarskantoor | D46: realisten.be | E46: Hasselt | G46: 0474 47 44 44 | H46: geen e-mail gevonden
A47: REF Vastgoed | B47: Vastgoed | C47: Makelaarskantoor | D47: ref-vastgoed.be | E47: Lier | G47: +32 3 480 84 44 | H47: geen e-mail gevonden
A48: Savemak Vastgoed | B48: Vastgoed | C48: Makelaarskantoor | D48: savemakvastgoed.be | E48: Lommel | F48: vastgoed@savemak.be | G48: 011 34 34 34 | H48: 20 jaar ervaring
A49: Sofie De Meester Vastgoed | B49: Vastgoed | C49: Makelaarskantoor | D49: sofiedemeestervastgoed.be | E49: Gent | F49: info@sofiedemeestervastgoed.be | G49: +32 9 324 05 05
A50: TOP Vastgoed | B50: Vastgoed | C50: Makelaarskantoor | D50: topvastgoed.be | E50: Wondelgem (Gent) | F50: info@topvastgoed.be | G50: 09 273 63 73
A51: TREVI Liège | B51: Vastgoed | C51: Makelaarskantoor | D51: trevi.be | E51: Liège | F51: info@treviliege.be | G51: 04 336 35 82 | H51: verkoop, verhuur & beheer
A52: Vansweevelt Vastgoed | B52: Vastgoed | C52: Makelaarskantoor | D52: vansweevelt.be | E52: Mechelen (ook actief in Kempen) | F52: info@vansweevelt.be | G52: +32 15 69 02 11 | H52: verkoop, verhuur & beheer
A53: Vast & Goed Makelaars | B53: Vastgoed | C53: Makelaarskantoor | D53: vastengoed.be | E53: Geel | F53: info@vastengoed.be | G53: 014 72 73 74
A54: Vastgoed Sinnaeve | B54: Vastgoed | C54: Makelaarskantoor | D54: vastgoedsinnaeve.be | E54: Koekelare | F54: info@vastgoedsinnaeve.be | G54: 0476 77 24 46 | H54: kantoren Koekelare & Roeselare
A55: Vastgoed Valkenborgh | B55: Vastgoed | C55: Makelaarskantoor | D55: vastgoedvalkenborgh.be | E55: Hasselt | G55: 0472 74 24 33 | H55: geen e-mail gevonden
A56: VB Vastgoed | B56: Vastgoed | C56: Makelaarskantoor | D56: vbvastgoed.be | E56: Antwerpen | F56: info@vbvastgoed.be | G56: +32 3 337 50 70 | H56: 6-7 kantoren
A57: Vivendi Vastgoed Turnhout | B57: Vastgoed | C57: Makelaarskantoor | D57: vivendivastgoedturnhout.be | E57: Turnhout | G57: +32 14 70 70 35 | H57: e-mail afgeschermd
A58: Agence Immobilière Sociale du Brabant Wallon | B58: Vastgoed | C58: Verhuur- & beheerkantoor | D58: aisbw.be | E58: Wavre | F58: info@aisbw.be | G58: 010 88 05 58 | H58: sociaal verhuurkantoor
A59: Agence Van den Abeele | B59: Vastgoed | C59: Verhuur- & beheerkantoor | D59: agencevandenabeele.be | E59: Brugge | F59: info@agencevandenabeele.be | G59: 050 33 39 76 | H59: vastgoedbeheer sinds 1930
A60: CSRE | B60: Vastgoed | C60: Verhuur- & beheerkantoor | D60: csre.be | E60: Kontich | F60: info@csre.be | G60: 03 435 78 20 | H60: rentmeester, syndicus, waardebepaling
A61: Estero Rentmeesters | B61: Vastgoed | C61: Verhuur- & beheerkantoor | D61: estero.be | E61: Erpe-Mere | F61: info@estero.be | G61: 0472 40 23 01 | H61: rentmeesterschap
A62: Huuringent | B62: Vastgoed | C62: Verhuur- & beheerkantoor | D62: huuringent.be | E62: Gent | F62: info@huuringent.be | G62: 09 269 69 69 | H62: verhuurkantoor
A63: Immobilière Legrand | B63: Vastgoed | C63: Verhuur- & beheerkantoor | D63: immolegrand.com | E63: Marcinelle (Charleroi) | F63: info@immolegrand.com | G63: 071 36 21 30 | H63: verhuur & huurbeheer
A64: Rencura | B64: Vastgoed | C64: Verhuur- & beheerkantoor | D64: rencura.be | E64: Gent / Antwerpen | F64: gent@rencura.be | G64: +32 9 330 21 00 | H64: huurbeheer (partner Syncura)
A65: Service Acor | B65: Vastgoed | C65: Verhuur- & beheerkantoor | D65: serviceacor.com | E65: Charleroi | F65: service.acor@gmail.com | G65: 071 32 02 08 | H65: huurbeheer
A66: TREVI Rentmeesterschap | B66: Vastgoed | C66: Verhuur- & beheerkantoor | D66: rentalmanagement.trevi.be | E66: Gent / Antwerpen | F66: rental.management@trevi.be | G66: +32 9 330 21 00 | H66: huurbeheer
A67: Abimo-Dewispelaere (ADW Immo) | B67: Vastgoed | C67: Syndicus / beheerkantoor | D67: adwimmo.be | E67: Heist (Knokke-Heist) / Knesselare | F67: info@adwimmo.be | G67: 050 51 39 94 | H67: syndicus & vastgoedbeheer
A68: Agence Sissau | B68: Vastgoed | C68: Syndicus / beheerkantoor | D68: sissau.be | E68: Middelkerke / Oostende | F68: info@sissau.be | G68: 059 30 19 91 | H68: syndic, verkoop & vakantieverhuur
A69: Algemeen Beheer 2.0 | B69: Vastgoed | C69: Syndicus / beheerkantoor | D69: algemeenbeheer.be | E69: Antwerpen | F69: info@algemeenbeheer.be | G69: 03 254 29 31 | H69: syndicus & rentmeester
... A71: Calix Syndic | B71: Vastgoed | C71: Syndicus / beheerkantoor | D71: calix-syndic.be | E71: Braine-le-Comte | F71: info@calix-syndic.be | G71: 067 85 35 42 | H71: 58 gebouwen in beheer
A72: De Syndicus | B72: Vastgoed | C72: Syndicus / beheerkantoor | D72: desyndicus.be | E72: Hasselt / Diest / Leuven | G72: +32 11 26 40 70 | H72: >300 gebouwen in beheer; geen e-mail in zoekresultaat
A73: Den Anker Beheer | B73: Vastgoed | C73: Syndicus / beheerkantoor | D73: denankerbeheer.be | E73: Diest | F73: info@denankerbeheer.be | G73: 013 33 33 33
A74: Easy Syndic | B74: Vastgoed | C74: Syndicus / beheerkantoor | D74: easysyndic.be | E74: Antwerpen (+ Brussel, Gent, Hasselt, …) | F74: welkom@easysyndic.be | G74: +32 3 375 61 19 | H74: syndicus voor kleine mede-eigendommen (2-19 units)
A75: GOED! Syndicusbeheer | B75: Vastgoed | C75: Syndicus / beheerkantoor | D75: goedsyndicusbeheer.be | E75: Boortmeerbeek | F75: info@goedsyndicusbeheer.be | G75: 0479 37 22 72
A76: Habicom Beheer | B76: Vastgoed | C76: Syndicus / beheerkantoor | D76: habicombeheer.be | E76: Antwerpen | F76: hallo@habicom.be | G76: 03 449 42 41 | H76: syndicus & rentmeester
A77: Het Syndichuis | B77: Vastgoed | C77: Syndicus / beheerkantoor | D77: hetsyndichuis.be | E77: Oostende | F77: info@hetsyndichuis.be | G77: 059 51 75 01 | H77: >25 jaar
A78: L'OP Syndic | B78: Vastgoed | C78: Syndicus / beheerkantoor | D78: op.be | E78: Brussel | G78: +32 2 626 08 26 | H78: contactformulier
A79: La Gestion d'Immeubles | B79: Vastgoed | C79: Syndicus / beheerkantoor | D79: gestionimmeubles.be | E79: Brussel (Watermaal-Bosvoorde) | G79: +32 2 374 91 30 | H79: e-mail afgeschermd
A80: Max Beheer (Agentschap Vangronsveld) | B80: Vastgoed | C80: Syndicus / beheerkantoor | D80: maxbeheer.be | E80: Bilzen (+ Genk, Hasselt) | F80: syndic@maxbeheer.be | G80: 089 50 06 99 | H80: 3 kantoren (Bilzen, Genk, Hasselt)
A81: MRP Group | B81: Vastgoed | C81: Syndicus / beheerkantoor | D81: mrpgroup.be | E81: Wemmel | G81: +32 2 644 27 27 | H81: enkel persoonlijk skynet-adres vermeld
A82: Norm VastgoedBeheer | B82: Vastgoed | C82: Syndicus / beheerkantoor | D82: norm.be | E82: Waregem | G82: 056 72 38 23 | H82: geen e-mail gevonden
A83: Sea'ndicus (Parte Group) | B83: Vastgoed | C83: Syndicus / beheerkantoor | D83: seandicus.be | E83: Oostende | F83: info@seandicus.be | G83: +32 59 29 50 00 | H83: ±100 gebouwen in beheer
A84: Syncura | B84: Vastgoed | C84: Syndicus / beheerkantoor | D84: syncura.be | E84: Gent (+ kantoren Antwerpen, Brussel, Oostende, …) | F84: gent@syncura.be | G84: 09 280 80 34 | H84: >40 jaar; meerdere kantoren
A85: Syndic Beheer | B85: Vastgoed | C85: Syndicus / beheerkantoor | D85: syndic-beheer.com | E85: Oostende / Middelkerke | F85: info@syndic-beheer.com | G85: 059 33 92 80 | H85: 2 kantoren, ±6 medewerkers
A86: Syndicbeheer.be | B86: Vastgoed | C86: Syndicus / beheerkantoor | D86: syndicbeheer.be | E86: Gent | G86: 09 324 82 42 | H86: geen e-mail gevonden
A87: Syndicusdiensten.be | B87: Vastgoed | C87: Syndicus / beheerkantoor | D87: syndicusdiensten.be | E87: Heusden-Zolder (+ Hasselt, Leuven) | F87: info@syndicusdiensten.be | G87: 011 18 25 54 | H87: 106 gebouwen, team van 10
A88: Syndix aan Zee | B88: Vastgoed | C88: Syndicus / beheerkantoor | D88: syndixaanzee.be | E88: Oostduinkerke (Koksijde) | F88: info@syndixaanzee.be | G88: +32 58 52 08 18
A89: Synimmo | B89: Vastgoed | C89: Syndicus / beheerkantoor | D89: synimmo.be | E89: Buggenhout / Zele | F89: info@synimmo.be | G89: 052 44 40 08
A90: Truyens Vastgoed | B90: Vastgoed | C90: Syndicus / beheerkantoor | D90: truyensvastgoed.be | E90: Heusden-Zolder | F90: hallo@truyensvastgoed.be | G90: +32 11 42 85 18 | H90: syndicus
A91: Uw-Syndic | B91: Vastgoed | C91: Syndicus / beheerkantoor | D91: uw-syndic.be | E91: Sint-Niklaas | F91: info@uw-syndic.be | G91: 03 569 15 00
A92: Vlaemynck Vastgoedmanagement | B92: Vastgoed | C92: Syndicus / beheerkantoor | D92: vlaemynck.be | E92: Tielt | F92: ann@vlaemynck.be | G92: +32 51 40 40 10 | H92: ±150 gebouwen in beheer (W-Vl & kust); persoonlijk adres
A93: Ablimmo | B93: Vastgoed | C93: Kleinere vastgoedontwikkelaar | D93: ablimmo.be | E93: Aalst | F93: info@ablimmo.be | G93: 053 39 81 85 | H93: residentieel, retail, kmo
A94: C-Nest Groep | B94: Vastgoed | C94: Kleinere vastgoedontwikkelaar | D94: cnest.be | E94: Deinze | F94: info@cnest.be | G94: 056 66 59 45 | H94: residentiële projectontwikkeling Oost- en West-Vlaanderen
A95: Condius | B95: Vastgoed | C95: Kleinere vastgoedontwikkelaar | D95: condius.com | E95: Nieuwpoort | F95: info@condius.be | G95: +32 58 59 29 00 | H95: vastgoedontwikkeling aan de kust
A96: DDL Construct | B96: Vastgoed | C96: Kleinere vastgoedontwikkelaar | D96: ddlconstruct.be | E96: Kalmthout | F96: info@ddl-construct.be | H96: appartementsgebouwen & woningen; geen telefoon in zoekresultaat
A97: Fonders | B97: Vastgoed | C97: Kleinere vastgoedontwikkelaar | D97: fonders.be | E97: Jabbeke | F97: carl@fonders.be | G97: +32 473 32 64 64 | H97: projectontwikkelaar en bouwcoördinator; persoonlijk adres zaakvoerder
A98: Global Estate Group | B98: Vastgoed | C98: Kleinere vastgoedontwikkelaar | D98: globalestategroup.eu | E98: Oostkamp | F98: info@globalestategroup.eu | G98: +32 50 46 10 10 | H98: West- & Oost-Vlaanderen
A99: Martrick Projects | B99: Vastgoed | C99: Kleinere vastgoedontwikkelaar | D99: martrickprojects.be | E99: Knokke-Heist | F99: info@martrickprojects.be | G99: 0495 20 98 48 | H99: projecten van ±10 appartementen
A100: Tervia's | B100: Vastgoed | C100: Kleinere vastgoedontwikkelaar | D100: tervias.be | E100: Hulshout | F100: info@tervias.be | G100: +32 16 67 00 68 | H100: residentieel & kmo-units
A101: Wolf Invest | B101: Vastgoed | C101: Kleinere vastgoedontwikkelaar | D101: wolf-invest.be | E101: Limburg / Antwerpen | F101: info@wolf-invest.be | H101: kleinschalige appartementsprojecten; geen telefoon in zoekresultaat
