Workbook

Sheet Overzicht
A1: Koppelingen voor boekhoud- en accountantskantoren (Vlaanderen en Nederland)
A2: Opgesteld op 9 oktober 2026 voor Sprite. Volledige lijst en filters in het tabblad "Alle tools".
A4: Legenda
A5: Belang A | B5: Marktleider of onmisbaar: bijna elk kantoor in die regio gebruikt het of moet ermee werken.
A6: Belang B | B6: Breed gebruikt in een belangrijk segment (bijvoorbeeld grotere kantoren of bepaalde klanten).
A7: Belang C | B7: Niche of kleiner marktaandeel.
A8: P1 | B8: Eerste golf: nodig om kantoren in Vlaanderen te overtuigen. Hoog belang én een bruikbare API.
A9: P2 | B9: Tweede golf: belangrijk, maar beperkte API of vooral nuttig in Nederland.
A10: P3 | B10: Later of via de cloudbrowser.
A11: Open API | B11: Publieke API die je zelf kan aanspreken (soms met betaald developerplan).
A12: Partner-API | B12: API na aanvraag, overeenkomst of registratie bij de leverancier.
A13: Bestandsuitwisseling | B13: Geen API; koppelen via export/import (UBL, CODA, XML).
A14: Geen API → cloudbrowser | B14: Sprite werkt via de cloudbrowser ("toon het één keer").
A15: Zekerheid | B15: "Geverifieerd" = API-info nagekeken in documentatie of berichtgeving van de leverancier (okt. 2026). "Te verifiëren" = op basis van marktkennis, nog bevestigen bij de leverancier.
A17: Aantal tools per belang en land
A18: Belang | B18: BE | C18: NL | D18: BE + NL | E18: Totaal
A19: A | B19: =COUNTIFS('Alle tools'!$F$2:$F$81,$A19,'Alle tools'!$E$2:$E$81,B$18) | C19: =COUNTIFS('Alle tools'!$F$2:$F$81,$A19,'Alle tools'!$E$2:$E$81,C$18) | D19: =COUNTIFS('Alle tools'!$F$2:$F$81,$A19,'Alle tools'!$E$2:$E$81,D$18) | E19: =SUM(B19:D19)
A20: B | B20: =COUNTIFS('Alle tools'!$F$2:$F$81,$A20,'Alle tools'!$E$2:$E$81,B$18) | C20: =COUNTIFS('Alle tools'!$F$2:$F$81,$A20,'Alle tools'!$E$2:$E$81,C$18) | D20: =COUNTIFS('Alle tools'!$F$2:$F$81,$A20,'Alle tools'!$E$2:$E$81,D$18) | E20: =SUM(B20:D20)
A21: C | B21: =COUNTIFS('Alle tools'!$F$2:$F$81,$A21,'Alle tools'!$E$2:$E$81,B$18) | C21: =COUNTIFS('Alle tools'!$F$2:$F$81,$A21,'Alle tools'!$E$2:$E$81,C$18) | D21: =COUNTIFS('Alle tools'!$F$2:$F$81,$A21,'Alle tools'!$E$2:$E$81,D$18) | E21: =SUM(B21:D21)
A22: Totaal | B22: =SUM(B19:B21) | C22: =SUM(C19:C21) | D22: =SUM(D19:D21) | E22: =SUM(E19:E21)
A24: Aantal tools per prioriteit en type koppeling
A25: Prioriteit | B25: Open API | C25: Partner-API | D25: Bestandsuitwisseling | E25: Geen API → cloudbrowser | F25: Totaal
A26: P1 | B26: =COUNTIFS('Alle tools'!$J$2:$J$81,$A26,'Alle tools'!$I$2:$I$81,B$25) | C26: =COUNTIFS('Alle tools'!$J$2:$J$81,$A26,'Alle tools'!$I$2:$I$81,C$25) | D26: =COUNTIFS('Alle tools'!$J$2:$J$81,$A26,'Alle tools'!$I$2:$I$81,D$25) | E26: =COUNTIFS('Alle tools'!$J$2:$J$81,$A26,'Alle tools'!$I$2:$I$81,E$25) | F26: =SUM(B26:E26)
A27: P2 | B27: =COUNTIFS('Alle tools'!$J$2:$J$81,$A27,'Alle tools'!$I$2:$I$81,B$25) | C27: =COUNTIFS('Alle tools'!$J$2:$J$81,$A27,'Alle tools'!$I$2:$I$81,C$25) | D27: =COUNTIFS('Alle tools'!$J$2:$J$81,$A27,'Alle tools'!$I$2:$I$81,D$25) | E27: =COUNTIFS('Alle tools'!$J$2:$J$81,$A27,'Alle tools'!$I$2:$I$81,E$25) | F27: =SUM(B27:E27)
A28: P3 | B28: =COUNTIFS('Alle tools'!$J$2:$J$81,$A28,'Alle tools'!$I$2:$I$81,B$25) | C28: =COUNTIFS('Alle tools'!$J$2:$J$81,$A28,'Alle tools'!$I$2:$I$81,C$25) | D28: =COUNTIFS('Alle tools'!$J$2:$J$81,$A28,'Alle tools'!$I$2:$I$81,D$25) | E28: =COUNTIFS('Alle tools'!$J$2:$J$81,$A28,'Alle tools'!$I$2:$I$81,E$25) | F28: =SUM(B28:E28)
A30: Aanbevolen startvolgorde voor Vlaanderen (P1, belang A eerst)
A31: Stap | B31: Tool | C31: Waarom
A32: 1 | B32: Outlook, Excel, SharePoint (Microsoft 365) | C32: Elke taak begint in de mailbox; één Graph-koppeling dekt mail, documenten en Excel.
A33: 2 | B33: Codabox | C33: Bankafschriften en loonboekingen voor bijna elk dossier; officiële API.
A34: 3 | B34: Octopus, Yuki, Exact Online, WinBooks, Adsolut | C34: De vijf grote pakketten bij Vlaamse kantoren, allemaal met API. Overweeg Chift om er meerdere tegelijk te ontsluiten.
A35: 4 | B35: Clearfacts en Billit | C35: Aankoopfacturen en Peppol-facturen; e-facturatie is sinds 2026 verplicht.
A36: 5 | B36: Silverfin en AdminPulse | C36: Afsluiting, deadlines en kantoorbeheer: hier zit de opvolging van elk dossier.
A37: 6 | B37: MyMinfin-API en Intervat-API | C37: Documenten en btw-aangiftes rechtstreeks, zonder in te loggen met itsme.
A38: 7 | B38: KBO en Companyweb | C38: Onboarding en antiwitwascontrole van nieuwe klanten.
A39: 8 | B39: Horus en Ponto | C39: Snelgroeiend pakket en bankdata buiten CODA om.
A41: Aandachtspunten
A42: • Overheidsportalen (MyMinfin, Tax-on-web, Biztax) vragen een login met itsme of eID. Gebruik waar het kan de officiële API's met mandaat in plaats van de cloudbrowser.
A43: • Sage BOB 50 en Venice hebben geen publieke API. Werk via Codabox, BOB Demat of de cloudbrowser.
A44: • Voor Nederland zijn Exact Online, Twinfield, Basecone, SnelStart, Loket.nl en de KVK API de eerste keuzes; Nextens heeft geen bekende publieke API.
A45: • De informatie over marktposities komt grotendeels van leveranciers zelf; er is geen onafhankelijk marktaandeelonderzoek voor Belgische kantoren gevonden.

Sheet Alle tools
A1: # | B1: Categorie | C1: Tool | D1: Leverancier | E1: Land | F1: Belang | G1: Wie gebruikt het | H1: API-mogelijkheid | I1: Type koppeling | J1: Prioriteit Sprite | K1: Wat Sprite ermee doet | L1: Zekerheid API-info
A2: 1 | B2: Afsluiting & rapportering | C2: Silverfin | D2: Visma | E2: BE + NL | F2: A | G2: Jaarafsluiting, werkprogramma's en rapportering; zeer breed in Vlaanderen | H2: Open API (OAuth2), API-overeenkomst via Customer Success Manager | I2: Partner-API | J2: P1 | K2: Werkprogramma's voorbereiden, cijfers en dossierstatus ophalen | L2: Geverifieerd
A3: 2 | B3: Bank | C3: Isabel 6 & Ponto | D3: Isabel (BE) | E3: BE | F3: A | G3: Bankieren en open banking voor bedrijven; Ponto is de PSD2-API | H3: Ponto open banking API | I3: Open API | J3: P1 | K3: Banktransacties ophalen en betalingen klaarzetten (met akkoord) | L3: Te verifiëren
A4: 3 | B4: Boekhoudpakket | C4: Adsolut | D4: Wolters Kluwer | E4: BE | F4: A | G4: Cloudsuite van Wolters Kluwer, middelgrote en grote kantoren | H4: Public API via My.Adsolut.com, gratis registratie op api-portal.adsolut.com; scope wijzigt | I4: Partner-API | J4: P1 | K4: Boekhouding en kmo-beheer lezen/schrijven per vrijgegeven dossier | L4: Geverifieerd
A5: 4 | B5: Boekhoudpakket | C5: Exact Online | D5: Exact | E5: BE + NL | F5: A | G5: Breedst gebruikte cloudpakket in NL; groot in BE bij kantoren en kmo's | H5: REST API met OAuth2; aparte omgevingen BE/NL, betaald developerplan | I5: Open API | J5: P1 | K5: Boekingen, verkoop- en aankoopfacturen, relaties en saldi lezen en schrijven | L5: Geverifieerd
A6: 5 | B6: Boekhoudpakket | C6: Octopus | D6: Octopus (BE) | E6: BE | F6: A | G6: Volgens Octopus dagelijks >2.200 accountantskantoren, sterk in Vlaanderen | H6: Gratis open REST API, ~70 bestaande integraties | I6: Open API | J6: P1 | K6: Facturen inboeken, dagboeken en saldi ophalen, klantvragen beantwoorden met cijfers | L6: Geverifieerd
A7: 6 | B7: Boekhoudpakket | C7: SnelStart | D7: SnelStart | E7: NL | F7: A | G7: Zeer breed bij NL-mkb; kantoren werken in klantadministraties | H7: Open REST API (B2B-API, abonnement) | I7: Open API | J7: P1 | K7: Boekingen en facturen bij mkb-klanten | L7: Te verifiëren
A8: 7 | B8: Boekhoudpakket | C8: Twinfield | D8: Wolters Kluwer | E8: NL | F8: A | G8: Veel gebruikt door NL-kantoren die dagelijks boeken | H8: Webservices (SOAP) + REST, OAuth2 | I8: Open API | J8: P1 | K8: Boekingen, relaties, rapportages | L8: Te verifiëren
A9: 8 | B9: Boekhoudpakket | C9: WinBooks / WinBooks on Web | D9: WinBooks (BE) | E9: BE | F9: A | G9: Grote historische installed base bij Belgische kantoren | H9: REST API (WinBooks on Web, Bearer-token) + WinBooks Connect API (documentplatform) | I9: Open API | J9: P1 | K9: Dossiers lezen/schrijven, documenten via Connect naar het kantoor | L9: Geverifieerd
A10: 9 | B10: Boekhoudpakket | C10: Yuki | D10: Visma | E10: BE + NL | F10: A | G10: Cloudplatform voor kantoren, sinds 2024 deel van Visma | H10: Webservices/API met API-sleutel per administratie | I10: Open API | J10: P1 | K10: Documenten uploaden, boekingen en openstaande posten opvragen | L10: Geverifieerd
A11: 10 | B11: Documentverwerking | C11: Basecone | D11: Wolters Kluwer | E11: NL | F11: A | G11: Standaard scan- en herkenningstool bij NL-kantoren | H11: API | I11: Partner-API | J11: P1 | K11: Bonnen en facturen uploaden en status opvolgen | L11: Te verifiëren
A12: 11 | B12: Documentverwerking | C12: Clearfacts | D12: Clearfacts (BE) | E12: BE | F12: A | G12: Scannen en herkennen van aankoopfacturen voor kantoren | H12: Publieke GraphQL API (token of OpenID Connect) | I12: Open API | J12: P1 | K12: Facturen uploaden, status en boekvoorstellen opvolgen | L12: Geverifieerd
A13: 12 | B13: Documentverwerking | C13: Codabox (CODA, SODA, CARO) | D13: Codabox (BE) | E13: BE | F13: A | G13: Bankafschriften (CODA), loonboekingen (SODA), kredietkaart (CARO) voor bijna elk kantoor | H13: Codabox API V2 + Codabox Connect API, consent via MyCodabox | I13: Open API | J13: P1 | K13: Bankafschriften en loonboekingen automatisch per dossier ophalen | L13: Geverifieerd
... A81: 80 | B81: Overheid BE | C81: eJustice / Belgisch Staatsblad | D81: FOD Justitie | E81: BE | F81: C | G81: Publicaties en statutenwijzigingen | H81: Portaal | I81: Geen API → cloudbrowser | J81: P3 | K81: Publicaties van klanten opzoeken | L81: Te verifiëren
